{
  "export_date": "2026-02-09T06:42:55.769760",
  "season": "2025-26",
  "league": "Greek Basket League (ESAKE)",
  "player_count": 17,
  "players": [
    {
      "code": "34176278",
      "name": "Alec Peters",
      "team": "Olympiacos BC",
      "team_logo": "https://r2.thesportsdb.com/images/media/team/logo/r7b1lk1720039385.png",
      "position": "Power Forward",
      "nationality": "United States",
      "height_cm": 206,
      "height_feet": 6,
      "height_inches": 9,
      "birthdate": "1995-04-13",
      "birthplace": "Washington, Illinois",
      "headshot_url": "https://r2.thesportsdb.com/images/media/player/cutout/kwoz3e1698833189.png",
      "games_played": 16,
      "ppg": 13.5,
      "rpg": 4.5,
      "apg": 0.8,
      "game_log": [
        {
          "date": "Sun 9 Nov - 13:00",
          "opponent": "ΚΑΡΔΙΤΣΑΙΑΠΩΝΙΚΗ",
          "home_away": "Home",
          "team_score": 102,
          "opp_score": 82,
          "result": "W",
          "minutes": "00:26:44",
          "points": 15,
          "rebounds": 3,
          "assists": 0,
          "steals": 2,
          "blocks": 0,
          "turnovers": 2
        },
        {
          "date": "Sun 8 Feb - 13:00",
          "opponent": "ΠΡΟΜΗΘΕΑΣΠΑΤΡΑΣΒΙΚΟΣCOLA",
          "home_away": "Home",
          "team_score": 102,
          "opp_score": 87,
          "result": "W",
          "minutes": "00:20:00",
          "points": 24,
          "rebounds": 3,
          "assists": 0,
          "steals": 1,
          "blocks": 0,
          "turnovers": 1
        },
        {
          "date": "Sun 7 Dec - 13:00",
          "opponent": "ΑΕΚ",
          "home_away": "Home",
          "team_score": 100,
          "opp_score": 93,
          "result": "W",
          "minutes": "00:19:20",
          "points": 11,
          "rebounds": 3,
          "assists": 1,
          "steals": 2,
          "blocks": 0,
          "turnovers": 3
        },
        {
          "date": "Sun 5 Oct - 13:00",
          "opponent": "ΜΑΡΟΥΣΙCHERY",
          "home_away": "Away",
          "team_score": 100,
          "opp_score": 81,
          "result": "W",
          "minutes": "00:22:09",
          "points": 11,
          "rebounds": 3,
          "assists": 1,
          "steals": 1,
          "blocks": 0,
          "turnovers": 1
        },
        {
          "date": "Sun 4 Jan - 13:00",
          "opponent": "ΑΡΗΣBetsson",
          "home_away": "Away",
          "team_score": 95,
          "opp_score": 84,
          "result": "W",
          "minutes": "00:15:53",
          "points": 0,
          "rebounds": 4,
          "assists": 0,
          "steals": 0,
          "blocks": 0,
          "turnovers": 0
        },
        {
          "date": "Sun 26 Oct - 13:00",
          "opponent": "ΜΥΚΟΝΟΣBetsson BC",
          "home_away": "Away",
          "team_score": 91,
          "opp_score": 65,
          "result": "W",
          "minutes": "00:21:50",
          "points": 3,
          "rebounds": 5,
          "assists": 2,
          "steals": 2,
          "blocks": 0,
          "turnovers": 1
        },
        {
          "date": "Sun 25 Jan - 13:00",
          "opponent": "ΚΟΛΟΣΣΟΣ HHOTELSCOLLECTION",
          "home_away": "Away",
          "team_score": 98,
          "opp_score": 85,
          "result": "W",
          "minutes": "00:16:48",
          "points": 10,
          "rebounds": 5,
          "assists": 0,
          "steals": 0,
          "blocks": 0,
          "turnovers": 1
        },
        {
          "date": "Sun 23 Nov - 16:00",
          "opponent": "ΠΑΟΚ",
          "home_away": "Away",
          "team_score": 92,
          "opp_score": 81,
          "result": "W",
          "minutes": "00:17:15",
          "points": 4,
          "rebounds": 2,
          "assists": 1,
          "steals": 0,
          "blocks": 1,
          "turnovers": 1
        },
        {
          "date": "Sun 21 Dec - 13:00",
          "opponent": "ΚΟΛΟΣΣΟΣ HHOTELSCOLLECTION",
          "home_away": "Home",
          "team_score": 100,
          "opp_score": 86,
          "result": "W",
          "minutes": "00:23:13",
          "points": 16,
          "rebounds": 6,
          "assists": 0,
          "steals": 0,
          "blocks": 0,
          "turnovers": 1
        },
        {
          "date": "Sun 19 Oct - 13:00",
          "opponent": "ΠΑΝΙΩΝΙΟΣCOSMORAMATRAVEL",
          "home_away": "Home",
          "team_score": 81,
          "opp_score": 66,
          "result": "W",
          "minutes": "00:24:06",
          "points": 8,
          "rebounds": 6,
          "assists": 4,
          "steals": 1,
          "blocks": 0,
          "turnovers": 1
        },
        {
          "date": "Sun 16 Nov - 16:00",
          "opponent": "ΠΡΟΜΗΘΕΑΣΠΑΤΡΑΣΒΙΚΟΣCOLA",
          "home_away": "Away",
          "team_score": 88,
          "opp_score": 64,
          "result": "W",
          "minutes": "00:19:44",
          "points": 14,
          "rebounds": 7,
          "assists": 1,
          "steals": 4,
          "blocks": 0,
          "turnovers": 3
        },
        {
          "date": "Sun 14 Dec - 16:00",
          "opponent": "ΠΕΡΙΣΤΕΡΙBetsson",
          "home_away": "Away",
          "team_score": 105,
          "opp_score": 62,
          "result": "W",
          "minutes": "00:24:36",
          "points": 15,
          "rebounds": 6,
          "assists": 0,
          "steals": 0,
          "blocks": 0,
          "turnovers": 1
        },
        {
          "date": "Sun 12 Oct - 19:00",
          "opponent": "ΠΑΝΑΘΗΝΑΪΚΟΣAKTOR",
          "home_away": "Home",
          "team_score": 90,
          "opp_score": 86,
          "result": "W",
          "minutes": "00:10:00",
          "points": 6,
          "rebounds": 2,
          "assists": 1,
          "steals": 1,
          "blocks": 0,
          "turnovers": 0
        },
        {
          "date": "Sun 11 Jan - 13:00",
          "opponent": "ΚΑΡΔΙΤΣΑΙΑΠΩΝΙΚΗ",
          "home_away": "Away",
          "team_score": 120,
          "opp_score": 80,
          "result": "W",
          "minutes": "00:30:00",
          "points": 35,
          "rebounds": 6,
          "assists": 0,
          "steals": 0,
          "blocks": 0,
          "turnovers": 1
        },
        {
          "date": "Sat 31 Jan - 18:15",
          "opponent": "ΠΕΡΙΣΤΕΡΙBetsson",
          "home_away": "Home",
          "team_score": 94,
          "opp_score": 71,
          "result": "W",
          "minutes": "00:30:03",
          "points": 29,
          "rebounds": 3,
          "assists": 0,
          "steals": 2,
          "blocks": 0,
          "turnovers": 1
        },
        {
          "date": "Sat 17 Jan - 16:00",
          "opponent": "ΜΑΡΟΥΣΙCHERY",
          "home_away": "Home",
          "team_score": 104,
          "opp_score": 89,
          "result": "W",
          "minutes": "00:21:38",
          "points": 15,
          "rebounds": 8,
          "assists": 2,
          "steals": 0,
          "blocks": 1,
          "turnovers": 0
        }
      ],
      "description": "Alec Peters (born April 13, 1995) is an American-born naturalized Bosnian professional basketball player for Olympiacos of the Greek Basket League (GBL) and the EuroLeague. He played college basketball for Valparaiso University, where he was an All-American in 2017."
    },
    {
      "code": "34165860",
      "name": "Bryn Forbes",
      "team": "Aris BC",
      "team_logo": "https://r2.thesportsdb.com/images/media/team/badge/l0tssh1739659466.png",
      "position": "Shooting Guard",
      "nationality": "United States",
      "height_cm": 188,
      "height_feet": 6,
      "height_inches": 2,
      "birthdate": "1993-07-23",
      "birthplace": "Lansing, Michigan",
      "headshot_url": "https://r2.thesportsdb.com/images/media/player/cutout/9ugq3j1686764316.png",
      "games_played": 6,
      "ppg": 10.5,
      "rpg": 2.2,
      "apg": 0.7,
      "game_log": [
        {
          "date": "Sat 8 Nov - 16:00",
          "opponent": "ΜΥΚΟΝΟΣBetsson BC",
          "home_away": "Home",
          "team_score": 78,
          "opp_score": 61,
          "result": "W",
          "minutes": "00:19:27",
          "points": 9,
          "rebounds": 3,
          "assists": 1,
          "steals": 2,
          "blocks": 0,
          "turnovers": 2
        },
        {
          "date": "Sat 4 Oct - 16:00",
          "opponent": "ΚΑΡΔΙΤΣΑΙΑΠΩΝΙΚΗ",
          "home_away": "Away",
          "team_score": 77,
          "opp_score": 91,
          "result": "L",
          "minutes": "00:34:57",
          "points": 17,
          "rebounds": 5,
          "assists": 1,
          "steals": 1,
          "blocks": 0,
          "turnovers": 1
        },
        {
          "date": "Sat 25 Oct - 18:15",
          "opponent": "ΠΑΝΙΩΝΙΟΣCOSMORAMATRAVEL",
          "home_away": "Away",
          "team_score": 90,
          "opp_score": 73,
          "result": "W",
          "minutes": "00:24:57",
          "points": 13,
          "rebounds": 1,
          "assists": 1,
          "steals": 1,
          "blocks": 0,
          "turnovers": 0
        },
        {
          "date": "Sat 18 Oct - 19:00",
          "opponent": "ΜΑΡΟΥΣΙCHERY",
          "home_away": "Away",
          "team_score": 103,
          "opp_score": 108,
          "result": "L",
          "minutes": "00:29:14",
          "points": 16,
          "rebounds": 2,
          "assists": 1,
          "steals": 0,
          "blocks": 0,
          "turnovers": 2
        },
        {
          "date": "Sat 11 Oct - 16:00",
          "opponent": "ΚΟΛΟΣΣΟΣ HHOTELSCOLLECTION",
          "home_away": "Home",
          "team_score": 65,
          "opp_score": 73,
          "result": "L",
          "minutes": "00:29:15",
          "points": 5,
          "rebounds": 1,
          "assists": 0,
          "steals": 1,
          "blocks": 0,
          "turnovers": 3
        },
        {
          "date": "Sat 1 Nov - 18:15",
          "opponent": "ΠΑΟΚ",
          "home_away": "Home",
          "team_score": 73,
          "opp_score": 78,
          "result": "L",
          "minutes": "00:20:23",
          "points": 3,
          "rebounds": 1,
          "assists": 0,
          "steals": 1,
          "blocks": 0,
          "turnovers": 0
        }
      ],
      "description": "Bryn Jerrel Forbes (born July 23, 1993) is an American professional basketball player for Aris of the Greek Basketball League and the EuroCup. He played college basketball for Cleveland State and Michigan State, and became a reliable three-point shooter. He plays both guard positions."
    },
    {
      "code": "34181717",
      "name": "Darral Willis",
      "team": "Aris BC",
      "team_logo": "https://r2.thesportsdb.com/images/media/team/badge/l0tssh1739659466.png",
      "position": "Small Forward",
      "nationality": "Cyprus",
      "height_cm": 206,
      "height_feet": 6,
      "height_inches": 9,
      "birthdate": "1996-01-21",
      "birthplace": "Madison, Wisconsin, USA",
      "headshot_url": "https://r2.thesportsdb.com/images/media/player/cutout/en1sk21743244993.png",
      "games_played": 0,
      "ppg": 0,
      "rpg": 0,
      "apg": 0,
      "game_log": [],
      "description": "Darral Willis Jr. (born January 21, 1996) is an American-born naturalized Cypriot professional basketball player for Aris Thessaloniki of the Greek Basketball League (GBL). Born and raised in Madison, Wisconsin, Willis played high school basketball at Madison Memorial High School]. After two years at Pearl River and two years at Wichita State Willis entered the 2018 NBA draft but was not selected in the draft's two rounds."
    },
    {
      "code": "34165387",
      "name": "Daryl Macon",
      "team": "Maroussi B.C.",
      "team_logo": "https://r2.thesportsdb.com/images/media/team/badge/owpnus1700046872.png",
      "position": "Shooting Guard",
      "nationality": "United States",
      "height_cm": 191,
      "height_feet": 6,
      "height_inches": 3,
      "birthdate": "1995-11-29",
      "birthplace": "Little Rock, Arkansas",
      "headshot_url": "https://r2.thesportsdb.com/images/media/player/cutout/ufqo851550047447.png",
      "games_played": 17,
      "ppg": 13.2,
      "rpg": 2.6,
      "apg": 5.3,
      "game_log": [
        {
          "date": "Tue 30 Dec - 18:30",
          "opponent": "ΠΑΝΑΘΗΝΑΪΚΟΣAKTOR",
          "home_away": "Home",
          "team_score": 89,
          "opp_score": 99,
          "result": "L",
          "minutes": "00:28:16",
          "points": 9,
          "rebounds": 1,
          "assists": 4,
          "steals": 0,
          "blocks": 0,
          "turnovers": 4
        },
        {
          "date": "Sun 5 Oct - 13:00",
          "opponent": "ΟΛΥΜΠΙΑΚΟΣ",
          "home_away": "Home",
          "team_score": 81,
          "opp_score": 100,
          "result": "L",
          "minutes": "00:26:32",
          "points": 20,
          "rebounds": 3,
          "assists": 6,
          "steals": 0,
          "blocks": 0,
          "turnovers": 4
        },
        {
          "date": "Sun 4 Jan - 13:00",
          "opponent": "ΚΟΛΟΣΣΟΣ HHOTELSCOLLECTION",
          "home_away": "Away",
          "team_score": 76,
          "opp_score": 90,
          "result": "L",
          "minutes": "00:25:56",
          "points": 8,
          "rebounds": 3,
          "assists": 4,
          "steals": 0,
          "blocks": 0,
          "turnovers": 5
        },
        {
          "date": "Sun 25 Jan - 15:45",
          "opponent": "ΠΑΝΑΘΗΝΑΪΚΟΣAKTOR",
          "home_away": "Away",
          "team_score": 81,
          "opp_score": 92,
          "result": "L",
          "minutes": "00:19:12",
          "points": 13,
          "rebounds": 0,
          "assists": 4,
          "steals": 1,
          "blocks": 0,
          "turnovers": 1
        },
        {
          "date": "Sun 23 Nov - 13:00",
          "opponent": "ΗΡΑΚΛΗΣ",
          "home_away": "Home",
          "team_score": 87,
          "opp_score": 92,
          "result": "L",
          "minutes": "00:28:54",
          "points": 8,
          "rebounds": 0,
          "assists": 7,
          "steals": 0,
          "blocks": 0,
          "turnovers": 1
        },
        {
          "date": "Sun 21 Dec - 16:00",
          "opponent": "ΚΑΡΔΙΤΣΑΙΑΠΩΝΙΚΗ",
          "home_away": "Away",
          "team_score": 87,
          "opp_score": 103,
          "result": "L",
          "minutes": "00:17:22",
          "points": 6,
          "rebounds": 2,
          "assists": 3,
          "steals": 0,
          "blocks": 0,
          "turnovers": 0
        },
        {
          "date": "Sun 2 Nov - 16:00",
          "opponent": "ΜΥΚΟΝΟΣBetsson BC",
          "home_away": "Away",
          "team_score": 75,
          "opp_score": 77,
          "result": "L",
          "minutes": "00:26:13",
          "points": 12,
          "rebounds": 2,
          "assists": 5,
          "steals": 1,
          "blocks": 0,
          "turnovers": 3
        },
        {
          "date": "Sun 14 Dec - 13:00",
          "opponent": "ΠΑΟΚ",
          "home_away": "Home",
          "team_score": 87,
          "opp_score": 97,
          "result": "L",
          "minutes": "00:18:41",
          "points": 8,
          "rebounds": 1,
          "assists": 5,
          "steals": 1,
          "blocks": 0,
          "turnovers": 2
        },
        {
          "date": "Sun 11 Jan - 16:00",
          "opponent": "ΠΡΟΜΗΘΕΑΣΠΑΤΡΑΣΒΙΚΟΣCOLA",
          "home_away": "Home",
          "team_score": 96,
          "opp_score": 78,
          "result": "W",
          "minutes": "00:26:45",
          "points": 14,
          "rebounds": 6,
          "assists": 9,
          "steals": 2,
          "blocks": 1,
          "turnovers": 4
        },
        {
          "date": "Sun 1 Feb - 13:00",
          "opponent": "ΠΑΝΙΩΝΙΟΣCOSMORAMATRAVEL",
          "home_away": "Home",
          "team_score": 97,
          "opp_score": 105,
          "result": "L",
          "minutes": "00:32:05",
          "points": 18,
          "rebounds": 3,
          "assists": 6,
          "steals": 1,
          "blocks": 0,
          "turnovers": 1
        },
        {
          "date": "Sat 8 Nov - 18:15",
          "opponent": "ΠΑΝΙΩΝΙΟΣCOSMORAMATRAVEL",
          "home_away": "Away",
          "team_score": 92,
          "opp_score": 80,
          "result": "W",
          "minutes": "00:28:23",
          "points": 17,
          "rebounds": 3,
          "assists": 6,
          "steals": 1,
          "blocks": 0,
          "turnovers": 1
        },
        {
          "date": "Sat 7 Feb - 18:00",
          "opponent": "ΑΕΚ",
          "home_away": "Away",
          "team_score": 74,
          "opp_score": 83,
          "result": "L",
          "minutes": "00:19:28",
          "points": 15,
          "rebounds": 1,
          "assists": 1,
          "steals": 0,
          "blocks": 0,
          "turnovers": 3
        },
        {
          "date": "Sat 6 Dec - 18:15",
          "opponent": "ΠΕΡΙΣΤΕΡΙBetsson",
          "home_away": "Away",
          "team_score": 78,
          "opp_score": 80,
          "result": "L",
          "minutes": "00:26:47",
          "points": 21,
          "rebounds": 5,
          "assists": 3,
          "steals": 0,
          "blocks": 0,
          "turnovers": 3
        },
        {
          "date": "Sat 18 Oct - 19:00",
          "opponent": "ΑΡΗΣBetsson",
          "home_away": "Home",
          "team_score": 108,
          "opp_score": 103,
          "result": "W",
          "minutes": "00:27:45",
          "points": 23,
          "rebounds": 1,
          "assists": 3,
          "steals": 0,
          "blocks": 0,
          "turnovers": 1
        },
        {
          "date": "Sat 17 Jan - 16:00",
          "opponent": "ΟΛΥΜΠΙΑΚΟΣ",
          "home_away": "Away",
          "team_score": 89,
          "opp_score": 104,
          "result": "L",
          "minutes": "00:31:37",
          "points": 10,
          "rebounds": 5,
          "assists": 12,
          "steals": 3,
          "blocks": 1,
          "turnovers": 2
        },
        {
          "date": "Sat 15 Nov - 18:15",
          "opponent": "ΑΕΚ",
          "home_away": "Home",
          "team_score": 82,
          "opp_score": 103,
          "result": "L",
          "minutes": "00:27:19",
          "points": 11,
          "rebounds": 4,
          "assists": 8,
          "steals": 0,
          "blocks": 0,
          "turnovers": 3
        },
        {
          "date": "Sat 11 Oct - 19:00",
          "opponent": "ΠΡΟΜΗΘΕΑΣΠΑΤΡΑΣΒΙΚΟΣCOLA",
          "home_away": "Away",
          "team_score": 88,
          "opp_score": 93,
          "result": "L",
          "minutes": "00:28:16",
          "points": 12,
          "rebounds": 5,
          "assists": 4,
          "steals": 0,
          "blocks": 0,
          "turnovers": 1
        }
      ],
      "description": "Daryl Macon Jr. (born November 29, 1995) is an American professional basketball player for Maroussi of the Greek Basketball League. He played college basketball for Holmes Community College and the Arkansas Razorbacks."
    },
    {
      "code": "34203391",
      "name": "Devin Cannady",
      "team": "Mykonos BC",
      "team_logo": "https://r2.thesportsdb.com/images/media/team/badge/ug2izi1760353764.png",
      "position": "Point Guard",
      "nationality": "United States",
      "height_cm": 188,
      "height_feet": 6,
      "height_inches": 2,
      "birthdate": "1996-05-21",
      "birthplace": "Mishawaka, Indiana, U.S.",
      "headshot_url": "https://r2.thesportsdb.com/images/media/player/cutout/rnnmgi1674412602.png",
      "games_played": 15,
      "ppg": 10.4,
      "rpg": 3.7,
      "apg": 2.1,
      "game_log": [
        {
          "date": "Sun 26 Oct - 13:00",
          "opponent": "ΟΛΥΜΠΙΑΚΟΣ",
          "home_away": "Home",
          "team_score": 65,
          "opp_score": 91,
          "result": "L",
          "minutes": "00:27:34",
          "points": 10,
          "rebounds": 2,
          "assists": 5,
          "steals": 0,
          "blocks": 0,
          "turnovers": 3
        },
        {
          "date": "Sun 2 Nov - 16:00",
          "opponent": "ΜΑΡΟΥΣΙCHERY",
          "home_away": "Home",
          "team_score": 77,
          "opp_score": 75,
          "result": "W",
          "minutes": "00:29:59",
          "points": 10,
          "rebounds": 4,
          "assists": 3,
          "steals": 0,
          "blocks": 0,
          "turnovers": 2
        },
        {
          "date": "Sun 18 Jan - 13:00",
          "opponent": "ΚΟΛΟΣΣΟΣ HHOTELSCOLLECTION",
          "home_away": "Home",
          "team_score": 67,
          "opp_score": 84,
          "result": "L",
          "minutes": "00:32:31",
          "points": 19,
          "rebounds": 6,
          "assists": 1,
          "steals": 0,
          "blocks": 0,
          "turnovers": 2
        },
        {
          "date": "Sun 12 Oct - 16:00",
          "opponent": "ΠΕΡΙΣΤΕΡΙBetsson",
          "home_away": "Away",
          "team_score": 83,
          "opp_score": 89,
          "result": "L",
          "minutes": "00:24:00",
          "points": 5,
          "rebounds": 1,
          "assists": 3,
          "steals": 0,
          "blocks": 1,
          "turnovers": 0
        },
        {
          "date": "Sun 11 Jan - 13:00",
          "opponent": "ΑΕΚ",
          "home_away": "Away",
          "team_score": 65,
          "opp_score": 90,
          "result": "L",
          "minutes": "00:29:15",
          "points": 11,
          "rebounds": 3,
          "assists": 3,
          "steals": 0,
          "blocks": 0,
          "turnovers": 2
        },
        {
          "date": "Sat 8 Nov - 16:00",
          "opponent": "ΑΡΗΣBetsson",
          "home_away": "Away",
          "team_score": 61,
          "opp_score": 78,
          "result": "L",
          "minutes": "00:22:08",
          "points": 5,
          "rebounds": 3,
          "assists": 1,
          "steals": 2,
          "blocks": 0,
          "turnovers": 1
        },
        {
          "date": "Sat 6 Dec - 16:00",
          "opponent": "ΠΡΟΜΗΘΕΑΣΠΑΤΡΑΣΒΙΚΟΣCOLA",
          "home_away": "Away",
          "team_score": 83,
          "opp_score": 103,
          "result": "L",
          "minutes": "00:16:39",
          "points": 4,
          "rebounds": 3,
          "assists": 2,
          "steals": 0,
          "blocks": 0,
          "turnovers": 1
        },
        {
          "date": "Sat 3 Jan - 15:45",
          "opponent": "ΠΑΟΚ",
          "home_away": "Home",
          "team_score": 101,
          "opp_score": 94,
          "result": "W",
          "minutes": "00:30:40",
          "points": 7,
          "rebounds": 1,
          "assists": 2,
          "steals": 1,
          "blocks": 0,
          "turnovers": 0
        },
        {
          "date": "Sat 27 Dec - 16:00",
          "opponent": "ΚΟΛΟΣΣΟΣ HHOTELSCOLLECTION",
          "home_away": "Away",
          "team_score": 97,
          "opp_score": 83,
          "result": "W",
          "minutes": "00:27:53",
          "points": 11,
          "rebounds": 6,
          "assists": 2,
          "steals": 0,
          "blocks": 0,
          "turnovers": 0
        },
        {
          "date": "Sat 24 Jan - 16:00",
          "opponent": "ΗΡΑΚΛΗΣ",
          "home_away": "Home",
          "team_score": 83,
          "opp_score": 80,
          "result": "W",
          "minutes": "00:26:07",
          "points": 16,
          "rebounds": 5,
          "assists": 3,
          "steals": 2,
          "blocks": 0,
          "turnovers": 0
        },
        {
          "date": "Sat 22 Nov - 16:00",
          "opponent": "ΠΑΝΑΘΗΝΑΪΚΟΣAKTOR",
          "home_away": "Home",
          "team_score": 65,
          "opp_score": 78,
          "result": "L",
          "minutes": "00:27:35",
          "points": 7,
          "rebounds": 1,
          "assists": 2,
          "steals": 0,
          "blocks": 0,
          "turnovers": 3
        },
        {
          "date": "Sat 20 Dec - 16:00",
          "opponent": "ΑΕΚ",
          "home_away": "Home",
          "team_score": 76,
          "opp_score": 77,
          "result": "L",
          "minutes": "00:27:39",
          "points": 16,
          "rebounds": 3,
          "assists": 2,
          "steals": 1,
          "blocks": 0,
          "turnovers": 1
        },
        {
          "date": "Sat 18 Oct - 17:00",
          "opponent": "ΗΡΑΚΛΗΣ",
          "home_away": "Away",
          "team_score": 80,
          "opp_score": 73,
          "result": "W",
          "minutes": "00:23:38",
          "points": 14,
          "rebounds": 5,
          "assists": 0,
          "steals": 2,
          "blocks": 0,
          "turnovers": 0
        },
        {
          "date": "Sat 15 Nov - 16:00",
          "opponent": "ΠΑΝΙΩΝΙΟΣCOSMORAMATRAVEL",
          "home_away": "Home",
          "team_score": 86,
          "opp_score": 77,
          "result": "W",
          "minutes": "00:33:44",
          "points": 18,
          "rebounds": 4,
          "assists": 3,
          "steals": 1,
          "blocks": 0,
          "turnovers": 2
        },
        {
          "date": "Sat 13 Dec - 16:00",
          "opponent": "ΚΑΡΔΙΤΣΑΙΑΠΩΝΙΚΗ",
          "home_away": "Home",
          "team_score": 75,
          "opp_score": 65,
          "result": "W",
          "minutes": "00:25:46",
          "points": 3,
          "rebounds": 8,
          "assists": 0,
          "steals": 0,
          "blocks": 0,
          "turnovers": 2
        }
      ],
      "description": "Devin Cannady (born May 21, 1996) is an American professional basketball player for Mykonos of the Greek Basketball League. He played college basketball for the Princeton Tigers."
    },
    {
      "code": "34219251",
      "name": "Donta Hall",
      "team": "Olympiacos BC",
      "team_logo": "https://r2.thesportsdb.com/images/media/team/logo/r7b1lk1720039385.png",
      "position": "Center",
      "nationality": "Azerbaijan",
      "height_cm": null,
      "height_feet": null,
      "height_inches": null,
      "birthdate": "1997-08-07",
      "birthplace": "Luverne, Alabama, U.S.",
      "headshot_url": "https://r2.thesportsdb.com/images/media/player/cutout/v70tco1760707823.png",
      "games_played": 17,
      "ppg": 10.4,
      "rpg": 5.4,
      "apg": 0.6,
      "game_log": [
        {
          "date": "Sun 9 Nov - 13:00",
          "opponent": "ΚΑΡΔΙΤΣΑΙΑΠΩΝΙΚΗ",
          "home_away": "Home",
          "team_score": 102,
          "opp_score": 82,
          "result": "W",
          "minutes": "00:21:23",
          "points": 15,
          "rebounds": 4,
          "assists": 2,
          "steals": 1,
          "blocks": 3,
          "turnovers": 2
        },
        {
          "date": "Sun 8 Feb - 13:00",
          "opponent": "ΠΡΟΜΗΘΕΑΣΠΑΤΡΑΣΒΙΚΟΣCOLA",
          "home_away": "Home",
          "team_score": 102,
          "opp_score": 87,
          "result": "W",
          "minutes": "00:20:00",
          "points": 15,
          "rebounds": 8,
          "assists": 0,
          "steals": 1,
          "blocks": 1,
          "turnovers": 0
        },
        {
          "date": "Sun 7 Dec - 13:00",
          "opponent": "ΑΕΚ",
          "home_away": "Home",
          "team_score": 100,
          "opp_score": 93,
          "result": "W",
          "minutes": "00:17:31",
          "points": 8,
          "rebounds": 7,
          "assists": 0,
          "steals": 1,
          "blocks": 1,
          "turnovers": 0
        },
        {
          "date": "Sun 5 Oct - 13:00",
          "opponent": "ΜΑΡΟΥΣΙCHERY",
          "home_away": "Away",
          "team_score": 100,
          "opp_score": 81,
          "result": "W",
          "minutes": "00:14:52",
          "points": 4,
          "rebounds": 0,
          "assists": 0,
          "steals": 0,
          "blocks": 0,
          "turnovers": 0
        },
        {
          "date": "Sun 4 Jan - 13:00",
          "opponent": "ΑΡΗΣBetsson",
          "home_away": "Away",
          "team_score": 95,
          "opp_score": 84,
          "result": "W",
          "minutes": "00:28:23",
          "points": 19,
          "rebounds": 5,
          "assists": 1,
          "steals": 1,
          "blocks": 2,
          "turnovers": 0
        },
        {
          "date": "Sun 26 Oct - 13:00",
          "opponent": "ΜΥΚΟΝΟΣBetsson BC",
          "home_away": "Away",
          "team_score": 91,
          "opp_score": 65,
          "result": "W",
          "minutes": "00:12:09",
          "points": 2,
          "rebounds": 4,
          "assists": 0,
          "steals": 1,
          "blocks": 2,
          "turnovers": 0
        },
        {
          "date": "Sun 25 Jan - 13:00",
          "opponent": "ΚΟΛΟΣΣΟΣ HHOTELSCOLLECTION",
          "home_away": "Away",
          "team_score": 98,
          "opp_score": 85,
          "result": "W",
          "minutes": "00:26:26",
          "points": 18,
          "rebounds": 8,
          "assists": 0,
          "steals": 0,
          "blocks": 2,
          "turnovers": 0
        },
        {
          "date": "Sun 23 Nov - 16:00",
          "opponent": "ΠΑΟΚ",
          "home_away": "Away",
          "team_score": 92,
          "opp_score": 81,
          "result": "W",
          "minutes": "00:20:00",
          "points": 3,
          "rebounds": 7,
          "assists": 0,
          "steals": 1,
          "blocks": 0,
          "turnovers": 0
        },
        {
          "date": "Sun 21 Dec - 13:00",
          "opponent": "ΚΟΛΟΣΣΟΣ HHOTELSCOLLECTION",
          "home_away": "Home",
          "team_score": 100,
          "opp_score": 86,
          "result": "W",
          "minutes": "00:21:58",
          "points": 10,
          "rebounds": 8,
          "assists": 3,
          "steals": 0,
          "blocks": 0,
          "turnovers": 1
        },
        {
          "date": "Sun 2 Nov - 13:00",
          "opponent": "ΗΡΑΚΛΗΣ",
          "home_away": "Home",
          "team_score": 103,
          "opp_score": 87,
          "result": "W",
          "minutes": "00:22:10",
          "points": 23,
          "rebounds": 6,
          "assists": 1,
          "steals": 1,
          "blocks": 1,
          "turnovers": 0
        },
        {
          "date": "Sun 19 Oct - 13:00",
          "opponent": "ΠΑΝΙΩΝΙΟΣCOSMORAMATRAVEL",
          "home_away": "Home",
          "team_score": 81,
          "opp_score": 66,
          "result": "W",
          "minutes": "00:19:20",
          "points": 16,
          "rebounds": 7,
          "assists": 0,
          "steals": 0,
          "blocks": 2,
          "turnovers": 0
        },
        {
          "date": "Sun 16 Nov - 16:00",
          "opponent": "ΠΡΟΜΗΘΕΑΣΠΑΤΡΑΣΒΙΚΟΣCOLA",
          "home_away": "Away",
          "team_score": 88,
          "opp_score": 64,
          "result": "W",
          "minutes": "00:18:13",
          "points": 10,
          "rebounds": 5,
          "assists": 0,
          "steals": 0,
          "blocks": 2,
          "turnovers": 0
        },
        {
          "date": "Sun 14 Dec - 16:00",
          "opponent": "ΠΕΡΙΣΤΕΡΙBetsson",
          "home_away": "Away",
          "team_score": 105,
          "opp_score": 62,
          "result": "W",
          "minutes": "00:14:33",
          "points": 6,
          "rebounds": 5,
          "assists": 0,
          "steals": 1,
          "blocks": 1,
          "turnovers": 0
        },
        {
          "date": "Sun 12 Oct - 19:00",
          "opponent": "ΠΑΝΑΘΗΝΑΪΚΟΣAKTOR",
          "home_away": "Home",
          "team_score": 90,
          "opp_score": 86,
          "result": "W",
          "minutes": "00:17:29",
          "points": 6,
          "rebounds": 4,
          "assists": 0,
          "steals": 0,
          "blocks": 0,
          "turnovers": 1
        },
        {
          "date": "Sun 11 Jan - 13:00",
          "opponent": "ΚΑΡΔΙΤΣΑΙΑΠΩΝΙΚΗ",
          "home_away": "Away",
          "team_score": 120,
          "opp_score": 80,
          "result": "W",
          "minutes": "00:20:00",
          "points": 13,
          "rebounds": 3,
          "assists": 1,
          "steals": 0,
          "blocks": 1,
          "turnovers": 0
        },
        {
          "date": "Sat 31 Jan - 18:15",
          "opponent": "ΠΕΡΙΣΤΕΡΙBetsson",
          "home_away": "Home",
          "team_score": 94,
          "opp_score": 71,
          "result": "W",
          "minutes": "00:24:30",
          "points": 1,
          "rebounds": 9,
          "assists": 2,
          "steals": 1,
          "blocks": 3,
          "turnovers": 0
        },
        {
          "date": "Sat 17 Jan - 16:00",
          "opponent": "ΜΑΡΟΥΣΙCHERY",
          "home_away": "Home",
          "team_score": 104,
          "opp_score": 89,
          "result": "W",
          "minutes": "00:14:48",
          "points": 7,
          "rebounds": 1,
          "assists": 1,
          "steals": 0,
          "blocks": 2,
          "turnovers": 1
        }
      ],
      "description": "Donta Hall (born August 7, 1997) is an American-born naturalized Azerbaijani professional basketball player for Olympiacos of the Greek Basketball League and the EuroLeague. He played college basketball for the Alabama Crimson Tide.\r\n\r\nHall grew up in Luverne, Alabama and attended Luverne High School, playing on the Tigers' junior varsity team in eighth grade. Hall's father Donald suffered a fatal heart attack at one of his junior varsity games. He was named first team Class 2A All-State after averaging 11.7 points, 10.1 rebounds and 6.7 blocks per game during his junior season as he led Luverne to a 24–2 record and the State final. Hall was rated the 81st best player in his class by ESPN and committed to play college basketball at Alabama at the end of his junior year over offers from UAB, Mississippi State and Troy. As a senior, Hall averaged a triple-double with 22.6 points, 18.1 rebounds and almost 12 blocks per game and was named the Class 2A Player of the Year in addition to being named first team All-State.\r\n\r\nAs a true freshman, Hall averaged 2.8 points, 4.3 rebounds and 1.7 blocks per game (6th in the Southeastern Conference). He entered the starting lineup for the Crimson Tide in December of his sophomore season, averaging six points, 5.5 rebounds and 1.4 blocks over 34 games (20 starts). As a junior, Hall set an Alabama single-season record, led the SEC, and finished second in the nation with a 72.6 field goal percentage while averaging 10.6 points per game and leading the team with 2.0 blocks (5th in the SEC) and 6.6 rebounds per game and was named to the SEC All-Defensive team.\r\n\r\nHall led the SEC with 8.8 rebounds per game as a senior while also averaging 10.5 points and 1.6 blocks per game. Hall finished his collegiate career with 1,014 points, 850 rebounds, and 228 blocked shots (seventh-most in Alabama history) in 135 games played with 85 starts."
    },
    {
      "code": "34201902",
      "name": "Frank Bartley",
      "team": "PAOK BC",
      "team_logo": "https://r2.thesportsdb.com/images/media/team/badge/sa18sr1492424960.png",
      "position": "Guard",
      "nationality": "United States",
      "height_cm": 191,
      "height_feet": 6,
      "height_inches": 3,
      "birthdate": "1994-02-25",
      "birthplace": "Baton Rouge, Louisiana, USA",
      "headshot_url": "https://r2.thesportsdb.com/images/media/player/cutout/d3xogy1743241897.png",
      "games_played": 16,
      "ppg": 17.8,
      "rpg": 4.2,
      "apg": 4.0,
      "game_log": [
        {
          "date": "Sun 9 Nov - 13:00",
          "opponent": "ΠΑΟΚ",
          "home_away": "Home",
          "team_score": 76,
          "opp_score": 78,
          "result": "L",
          "minutes": "00:29:33",
          "points": 13,
          "rebounds": 4,
          "assists": 5,
          "steals": 0,
          "blocks": 0,
          "turnovers": 1
        },
        {
          "date": "Sun 7 Dec - 13:00",
          "opponent": "ΟΛΥΜΠΙΑΚΟΣ",
          "home_away": "Away",
          "team_score": 93,
          "opp_score": 100,
          "result": "L",
          "minutes": "00:31:11",
          "points": 18,
          "rebounds": 2,
          "assists": 4,
          "steals": 1,
          "blocks": 0,
          "turnovers": 2
        },
        {
          "date": "Sun 12 Oct - 13:00",
          "opponent": "ΠΑΝΙΩΝΙΟΣCOSMORAMATRAVEL",
          "home_away": "Home",
          "team_score": 93,
          "opp_score": 73,
          "result": "W",
          "minutes": "00:23:33",
          "points": 15,
          "rebounds": 4,
          "assists": 1,
          "steals": 0,
          "blocks": 0,
          "turnovers": 1
        },
        {
          "date": "Sun 11 Jan - 13:00",
          "opponent": "ΜΥΚΟΝΟΣBetsson BC",
          "home_away": "Home",
          "team_score": 90,
          "opp_score": 65,
          "result": "W",
          "minutes": "00:35:15",
          "points": 15,
          "rebounds": 5,
          "assists": 7,
          "steals": 3,
          "blocks": 0,
          "turnovers": 5
        },
        {
          "date": "Sat 7 Feb - 18:00",
          "opponent": "ΜΑΡΟΥΣΙCHERY",
          "home_away": "Home",
          "team_score": 83,
          "opp_score": 74,
          "result": "W",
          "minutes": "00:35:48",
          "points": 21,
          "rebounds": 7,
          "assists": 5,
          "steals": 1,
          "blocks": 0,
          "turnovers": 3
        },
        {
          "date": "Sat 4 Oct - 16:00",
          "opponent": "ΚΟΛΟΣΣΟΣ HHOTELSCOLLECTION",
          "home_away": "Away",
          "team_score": 87,
          "opp_score": 85,
          "result": "W",
          "minutes": "00:34:45",
          "points": 18,
          "rebounds": 4,
          "assists": 4,
          "steals": 2,
          "blocks": 0,
          "turnovers": 2
        },
        {
          "date": "Sat 31 Jan - 18:15",
          "opponent": "ΚΟΛΟΣΣΟΣ HHOTELSCOLLECTION",
          "home_away": "Home",
          "team_score": 96,
          "opp_score": 83,
          "result": "W",
          "minutes": "00:32:41",
          "points": 15,
          "rebounds": 7,
          "assists": 5,
          "steals": 0,
          "blocks": 1,
          "turnovers": 1
        },
        {
          "date": "Sat 3 Jan - 18:15",
          "opponent": "ΠΡΟΜΗΘΕΑΣΠΑΤΡΑΣΒΙΚΟΣCOLA",
          "home_away": "Away",
          "team_score": 94,
          "opp_score": 86,
          "result": "W",
          "minutes": "00:35:09",
          "points": 22,
          "rebounds": 4,
          "assists": 7,
          "steals": 1,
          "blocks": 0,
          "turnovers": 2
        },
        {
          "date": "Sat 27 Dec - 16:00",
          "opponent": "ΑΡΗΣBetsson",
          "home_away": "Home",
          "team_score": 82,
          "opp_score": 76,
          "result": "W",
          "minutes": "00:33:05",
          "points": 9,
          "rebounds": 2,
          "assists": 5,
          "steals": 2,
          "blocks": 0,
          "turnovers": 0
        },
        {
          "date": "Sat 25 Oct - 17:30",
          "opponent": "ΗΡΑΚΛΗΣ",
          "home_away": "Away",
          "team_score": 82,
          "opp_score": 61,
          "result": "W",
          "minutes": "00:28:30",
          "points": 13,
          "rebounds": 8,
          "assists": 3,
          "steals": 4,
          "blocks": 0,
          "turnovers": 0
        },
        {
          "date": "Sat 20 Dec - 16:00",
          "opponent": "ΜΥΚΟΝΟΣBetsson BC",
          "home_away": "Away",
          "team_score": 77,
          "opp_score": 76,
          "result": "W",
          "minutes": "00:38:20",
          "points": 21,
          "rebounds": 5,
          "assists": 3,
          "steals": 1,
          "blocks": 0,
          "turnovers": 1
        },
        {
          "date": "Sat 18 Oct - 16:00",
          "opponent": "ΚΑΡΔΙΤΣΑΙΑΠΩΝΙΚΗ",
          "home_away": "Home",
          "team_score": 77,
          "opp_score": 62,
          "result": "W",
          "minutes": "00:30:23",
          "points": 19,
          "rebounds": 4,
          "assists": 4,
          "steals": 1,
          "blocks": 0,
          "turnovers": 2
        },
        {
          "date": "Sat 17 Jan - 18:15",
          "opponent": "ΚΑΡΔΙΤΣΑΙΑΠΩΝΙΚΗ",
          "home_away": "Away",
          "team_score": 79,
          "opp_score": 71,
          "result": "W",
          "minutes": "00:33:19",
          "points": 30,
          "rebounds": 3,
          "assists": 2,
          "steals": 2,
          "blocks": 1,
          "turnovers": 2
        },
        {
          "date": "Sat 15 Nov - 18:15",
          "opponent": "ΜΑΡΟΥΣΙCHERY",
          "home_away": "Away",
          "team_score": 103,
          "opp_score": 82,
          "result": "W",
          "minutes": "00:34:57",
          "points": 28,
          "rebounds": 6,
          "assists": 7,
          "steals": 0,
          "blocks": 0,
          "turnovers": 1
        },
        {
          "date": "Sat 13 Dec - 20:30",
          "opponent": "ΠΑΝΑΘΗΝΑΪΚΟΣAKTOR",
          "home_away": "Home",
          "team_score": 63,
          "opp_score": 101,
          "result": "L",
          "minutes": "00:32:04",
          "points": 16,
          "rebounds": 2,
          "assists": 1,
          "steals": 1,
          "blocks": 0,
          "turnovers": 1
        },
        {
          "date": "Sat 1 Nov - 16:00",
          "opponent": "ΠΕΡΙΣΤΕΡΙBetsson",
          "home_away": "Away",
          "team_score": 66,
          "opp_score": 79,
          "result": "L",
          "minutes": "00:25:57",
          "points": 11,
          "rebounds": 1,
          "assists": 1,
          "steals": 0,
          "blocks": 0,
          "turnovers": 0
        }
      ],
      "description": "Frank Bartley IV (born February 25, 1994) is an American professional basketball player for PAOK of the Greek Basketball League (GBL) and the FIBA Europe Cup (FEC). He played college basketball for the BYU Cougars and the Louisiana Ragin' Cajuns."
    },
    {
      "code": "34244334",
      "name": "Jacob Grandison",
      "team": "PAOK BC",
      "team_logo": "https://r2.thesportsdb.com/images/media/team/badge/sa18sr1492424960.png",
      "position": "Shooting Guard",
      "nationality": "Finland",
      "height_cm": 198,
      "height_feet": 6,
      "height_inches": 5,
      "birthdate": "1998-04-02",
      "birthplace": "San Francisco, California, U.S.",
      "headshot_url": "https://r2.thesportsdb.com/images/media/player/cutout/fxjxie1720362599.png",
      "games_played": 0,
      "ppg": 0,
      "rpg": 0,
      "apg": 0,
      "game_log": [],
      "description": "Jacob Alexander Grandison (born April 2, 1998) is an American-Finnish professional basketball player for PAOK Thessaloniki of the Greek Basketball League (GBL) and the FIBA Europe Cup. He also represents the Finnish national team in international competition. He played college basketball for the Holy Cross Crusaders, Illinois Fighting Illini, and the Duke Blue Devils."
    },
    {
      "code": "34165788",
      "name": "Jerian Grant",
      "team": "Panathinaikos BC",
      "team_logo": "https://r2.thesportsdb.com/images/media/team/badge/7cdjwz1767366987.png",
      "position": "Point Guard",
      "nationality": "United States",
      "height_cm": 193,
      "height_feet": 6,
      "height_inches": 3,
      "birthdate": "1992-10-09",
      "birthplace": "Silver Spring, Maryland",
      "headshot_url": "https://r2.thesportsdb.com/images/media/player/cutout/85ilmm1737712922.png",
      "games_played": 16,
      "ppg": 7.2,
      "rpg": 0.8,
      "apg": 3.4,
      "game_log": [
        {
          "date": "Tue 30 Dec - 18:30",
          "opponent": "ΜΑΡΟΥΣΙCHERY",
          "home_away": "Away",
          "team_score": 99,
          "opp_score": 89,
          "result": "W",
          "minutes": "00:20:07",
          "points": 0,
          "rebounds": 2,
          "assists": 7,
          "steals": 1,
          "blocks": 0,
          "turnovers": 0
        },
        {
          "date": "Sun 8 Feb - 16:00",
          "opponent": "ΚΑΡΔΙΤΣΑΙΑΠΩΝΙΚΗ",
          "home_away": "Away",
          "team_score": 78,
          "opp_score": 53,
          "result": "W",
          "minutes": "00:09:27",
          "points": 0,
          "rebounds": 0,
          "assists": 3,
          "steals": 0,
          "blocks": 0,
          "turnovers": 1
        },
        {
          "date": "Sun 7 Dec - 16:00",
          "opponent": "ΠΑΝΙΩΝΙΟΣCOSMORAMATRAVEL",
          "home_away": "Home",
          "team_score": 110,
          "opp_score": 66,
          "result": "W",
          "minutes": "00:12:23",
          "points": 5,
          "rebounds": 0,
          "assists": 3,
          "steals": 0,
          "blocks": 0,
          "turnovers": 0
        },
        {
          "date": "Sun 5 Oct - 16:00",
          "opponent": "ΠΑΟΚ",
          "home_away": "Home",
          "team_score": 93,
          "opp_score": 83,
          "result": "W",
          "minutes": "00:08:33",
          "points": 4,
          "rebounds": 0,
          "assists": 2,
          "steals": 0,
          "blocks": 0,
          "turnovers": 1
        },
        {
          "date": "Sun 26 Oct - 15:30",
          "opponent": "ΠΡΟΜΗΘΕΑΣΠΑΤΡΑΣΒΙΚΟΣCOLA",
          "home_away": "Home",
          "team_score": 91,
          "opp_score": 70,
          "result": "W",
          "minutes": "00:16:59",
          "points": 11,
          "rebounds": 1,
          "assists": 0,
          "steals": 0,
          "blocks": 0,
          "turnovers": 1
        },
        {
          "date": "Sun 25 Jan - 15:45",
          "opponent": "ΜΑΡΟΥΣΙCHERY",
          "home_away": "Home",
          "team_score": 92,
          "opp_score": 81,
          "result": "W",
          "minutes": "00:23:52",
          "points": 11,
          "rebounds": 1,
          "assists": 2,
          "steals": 0,
          "blocks": 0,
          "turnovers": 1
        },
        {
          "date": "Sun 19 Oct - 16:00",
          "opponent": "ΚΟΛΟΣΣΟΣ HHOTELSCOLLECTION",
          "home_away": "Away",
          "team_score": 90,
          "opp_score": 67,
          "result": "W",
          "minutes": "00:19:07",
          "points": 7,
          "rebounds": 0,
          "assists": 5,
          "steals": 1,
          "blocks": 0,
          "turnovers": 0
        },
        {
          "date": "Sun 18 Jan - 16:00",
          "opponent": "ΠΑΟΚ",
          "home_away": "Away",
          "team_score": 74,
          "opp_score": 69,
          "result": "W",
          "minutes": "00:36:56",
          "points": 10,
          "rebounds": 2,
          "assists": 3,
          "steals": 0,
          "blocks": 0,
          "turnovers": 3
        },
        {
          "date": "Sun 16 Nov - 18:15",
          "opponent": "ΑΡΗΣBetsson",
          "home_away": "Home",
          "team_score": 82,
          "opp_score": 77,
          "result": "W",
          "minutes": "00:22:08",
          "points": 11,
          "rebounds": 1,
          "assists": 4,
          "steals": 0,
          "blocks": 0,
          "turnovers": 1
        },
        {
          "date": "Sun 12 Oct - 19:00",
          "opponent": "ΟΛΥΜΠΙΑΚΟΣ",
          "home_away": "Away",
          "team_score": 86,
          "opp_score": 90,
          "result": "L",
          "minutes": "00:19:17",
          "points": 2,
          "rebounds": 1,
          "assists": 1,
          "steals": 0,
          "blocks": 0,
          "turnovers": 0
        },
        {
          "date": "Sun 11 Jan - 16:00",
          "opponent": "ΠΕΡΙΣΤΕΡΙBetsson",
          "home_away": "Home",
          "team_score": 94,
          "opp_score": 86,
          "result": "W",
          "minutes": "00:13:29",
          "points": 1,
          "rebounds": 1,
          "assists": 2,
          "steals": 0,
          "blocks": 0,
          "turnovers": 1
        },
        {
          "date": "Sun 1 Feb - 16:00",
          "opponent": "ΑΡΗΣBetsson",
          "home_away": "Away",
          "team_score": 95,
          "opp_score": 102,
          "result": "L",
          "minutes": "00:38:02",
          "points": 15,
          "rebounds": 1,
          "assists": 3,
          "steals": 1,
          "blocks": 0,
          "turnovers": 2
        },
        {
          "date": "Sat 8 Nov - 16:00",
          "opponent": "ΠΕΡΙΣΤΕΡΙBetsson",
          "home_away": "Away",
          "team_score": 89,
          "opp_score": 72,
          "result": "W",
          "minutes": "00:16:27",
          "points": 9,
          "rebounds": 0,
          "assists": 2,
          "steals": 2,
          "blocks": 0,
          "turnovers": 0
        },
        {
          "date": "Sat 22 Nov - 16:00",
          "opponent": "ΜΥΚΟΝΟΣBetsson BC",
          "home_away": "Away",
          "team_score": 78,
          "opp_score": 65,
          "result": "W",
          "minutes": "00:26:39",
          "points": 3,
          "rebounds": 1,
          "assists": 2,
          "steals": 0,
          "blocks": 0,
          "turnovers": 0
        },
        {
          "date": "Sat 20 Dec - 18:15",
          "opponent": "ΗΡΑΚΛΗΣ",
          "home_away": "Home",
          "team_score": 97,
          "opp_score": 82,
          "result": "W",
          "minutes": "00:29:44",
          "points": 13,
          "rebounds": 0,
          "assists": 8,
          "steals": 3,
          "blocks": 0,
          "turnovers": 1
        },
        {
          "date": "Sat 13 Dec - 20:30",
          "opponent": "ΑΕΚ",
          "home_away": "Away",
          "team_score": 101,
          "opp_score": 63,
          "result": "W",
          "minutes": "00:20:48",
          "points": 13,
          "rebounds": 2,
          "assists": 8,
          "steals": 0,
          "blocks": 0,
          "turnovers": 0
        }
      ],
      "description": "Holdyn Jerian Grant (born October 9, 1992) is an American professional basketball player for Panathinaikos of the Greek Basketball League (GBL) and the EuroLeague. He played college basketball with the University of Notre Dame and was considered one of the top college players in the nation for the 2014–15 season. After being selected with the 19th overall pick by the Washington Wizards in the 2015 NBA draft, his rights were sent to the Atlanta Hawks and then moved to the New York Knicks on draft night."
    },
    {
      "code": "34176338",
      "name": "Jordan Davis",
      "team": "Promitheas Patras BC",
      "team_logo": "https://r2.thesportsdb.com/images/media/team/badge/1o9c3f1739693075.png",
      "position": "Point Guard",
      "nationality": "Azerbaijan",
      "height_cm": 188,
      "height_feet": 6,
      "height_inches": 2,
      "birthdate": "1997-06-06",
      "birthplace": "Las Vegas, Nevada",
      "headshot_url": "https://r2.thesportsdb.com/images/media/player/cutout/4yqcka1742404363.png",
      "games_played": 0,
      "ppg": 0,
      "rpg": 0,
      "apg": 0,
      "game_log": [],
      "description": "Jordan Deangelo Davis (born June 6, 1997) is an American-born naturalized Azerbaijani professional basketball player for Promitheas Patras of the Greek Basketball League (GBL) and the Basketball Champions League (BCL). He played college basketball for the University of Northern Colorado, where in 2019 he was named the Big Sky Conference Player of the Year."
    },
    {
      "code": "34394589",
      "name": "Justin Wright-Foreman",
      "team": "Iraklis BC",
      "team_logo": "https://r2.thesportsdb.com/images/media/team/badge/anc9bw1759328517.png",
      "position": "Point Guard",
      "nationality": "United States",
      "height_cm": 183,
      "height_feet": 6,
      "height_inches": 0,
      "birthdate": "1997-10-27",
      "birthplace": "Queens, United States",
      "headshot_url": "https://www.thesportsdb.com/images/media/player/thumb/c8mc2o1769354915.jpg",
      "games_played": 16,
      "ppg": 18.6,
      "rpg": 4.0,
      "apg": 3.6,
      "game_log": [
        {
          "date": "Sun 23 Nov - 13:00",
          "opponent": "ΜΑΡΟΥΣΙCHERY",
          "home_away": "Away",
          "team_score": 92,
          "opp_score": 87,
          "result": "W",
          "minutes": "00:33:13",
          "points": 20,
          "rebounds": 4,
          "assists": 6,
          "steals": 0,
          "blocks": 0,
          "turnovers": 2
        },
        {
          "date": "Sun 2 Nov - 13:00",
          "opponent": "ΟΛΥΜΠΙΑΚΟΣ",
          "home_away": "Away",
          "team_score": 87,
          "opp_score": 103,
          "result": "L",
          "minutes": "00:28:56",
          "points": 20,
          "rebounds": 2,
          "assists": 1,
          "steals": 1,
          "blocks": 0,
          "turnovers": 5
        },
        {
          "date": "Sun 16 Nov - 13:00",
          "opponent": "ΚΟΛΟΣΣΟΣ HHOTELSCOLLECTION",
          "home_away": "Home",
          "team_score": 86,
          "opp_score": 71,
          "result": "W",
          "minutes": "00:34:15",
          "points": 17,
          "rebounds": 9,
          "assists": 7,
          "steals": 0,
          "blocks": 0,
          "turnovers": 3
        },
        {
          "date": "Sat 7 Feb - 18:15",
          "opponent": "ΠΕΡΙΣΤΕΡΙBetsson",
          "home_away": "Away",
          "team_score": 74,
          "opp_score": 92,
          "result": "L",
          "minutes": "00:34:38",
          "points": 17,
          "rebounds": 1,
          "assists": 6,
          "steals": 1,
          "blocks": 1,
          "turnovers": 5
        },
        {
          "date": "Sat 6 Dec - 18:15",
          "opponent": "ΚΑΡΔΙΤΣΑΙΑΠΩΝΙΚΗ",
          "home_away": "Away",
          "team_score": 87,
          "opp_score": 80,
          "result": "W",
          "minutes": "00:35:50",
          "points": 31,
          "rebounds": 5,
          "assists": 6,
          "steals": 1,
          "blocks": 0,
          "turnovers": 2
        },
        {
          "date": "Sat 4 Oct - 19:00",
          "opponent": "ΠΡΟΜΗΘΕΑΣΠΑΤΡΑΣΒΙΚΟΣCOLA",
          "home_away": "Home",
          "team_score": 90,
          "opp_score": 79,
          "result": "W",
          "minutes": "00:30:18",
          "points": 22,
          "rebounds": 4,
          "assists": 3,
          "steals": 0,
          "blocks": 0,
          "turnovers": 3
        },
        {
          "date": "Sat 31 Jan - 16:00",
          "opponent": "ΚΑΡΔΙΤΣΑΙΑΠΩΝΙΚΗ",
          "home_away": "Home",
          "team_score": 93,
          "opp_score": 73,
          "result": "W",
          "minutes": "00:07:52",
          "points": 0,
          "rebounds": 0,
          "assists": 1,
          "steals": 0,
          "blocks": 0,
          "turnovers": 1
        },
        {
          "date": "Sat 3 Jan - 18:15",
          "opponent": "ΠΕΡΙΣΤΕΡΙBetsson",
          "home_away": "Home",
          "team_score": 73,
          "opp_score": 59,
          "result": "W",
          "minutes": "00:32:17",
          "points": 18,
          "rebounds": 5,
          "assists": 3,
          "steals": 2,
          "blocks": 0,
          "turnovers": 4
        },
        {
          "date": "Sat 27 Dec - 18:15",
          "opponent": "ΠΑΝΙΩΝΙΟΣCOSMORAMATRAVEL",
          "home_away": "Home",
          "team_score": 80,
          "opp_score": 66,
          "result": "W",
          "minutes": "00:27:12",
          "points": 21,
          "rebounds": 7,
          "assists": 3,
          "steals": 1,
          "blocks": 0,
          "turnovers": 3
        },
        {
          "date": "Sat 25 Oct - 17:30",
          "opponent": "ΑΕΚ",
          "home_away": "Home",
          "team_score": 61,
          "opp_score": 82,
          "result": "L",
          "minutes": "00:20:58",
          "points": 11,
          "rebounds": 1,
          "assists": 1,
          "steals": 1,
          "blocks": 0,
          "turnovers": 2
        },
        {
          "date": "Sat 24 Jan - 16:00",
          "opponent": "ΜΥΚΟΝΟΣBetsson BC",
          "home_away": "Away",
          "team_score": 80,
          "opp_score": 83,
          "result": "L",
          "minutes": "00:23:40",
          "points": 12,
          "rebounds": 4,
          "assists": 2,
          "steals": 0,
          "blocks": 0,
          "turnovers": 9
        },
        {
          "date": "Sat 20 Dec - 18:15",
          "opponent": "ΠΑΝΑΘΗΝΑΪΚΟΣAKTOR",
          "home_away": "Away",
          "team_score": 82,
          "opp_score": 97,
          "result": "L",
          "minutes": "00:27:02",
          "points": 20,
          "rebounds": 2,
          "assists": 2,
          "steals": 2,
          "blocks": 0,
          "turnovers": 5
        },
        {
          "date": "Sat 18 Oct - 17:00",
          "opponent": "ΜΥΚΟΝΟΣBetsson BC",
          "home_away": "Home",
          "team_score": 73,
          "opp_score": 80,
          "result": "L",
          "minutes": "00:34:51",
          "points": 17,
          "rebounds": 10,
          "assists": 5,
          "steals": 1,
          "blocks": 0,
          "turnovers": 3
        },
        {
          "date": "Sat 13 Dec - 16:00",
          "opponent": "ΑΡΗΣBetsson",
          "home_away": "Home",
          "team_score": 80,
          "opp_score": 82,
          "result": "L",
          "minutes": "00:35:25",
          "points": 25,
          "rebounds": 5,
          "assists": 6,
          "steals": 1,
          "blocks": 0,
          "turnovers": 1
        },
        {
          "date": "Sat 11 Oct - 19:30",
          "opponent": "ΠΑΟΚ",
          "home_away": "Away",
          "team_score": 82,
          "opp_score": 84,
          "result": "L",
          "minutes": "00:25:37",
          "points": 19,
          "rebounds": 0,
          "assists": 4,
          "steals": 1,
          "blocks": 0,
          "turnovers": 1
        },
        {
          "date": "Sat 10 Jan - 15:30",
          "opponent": "ΑΡΗΣBetsson",
          "home_away": "Away",
          "team_score": 76,
          "opp_score": 78,
          "result": "L",
          "minutes": "00:37:24",
          "points": 27,
          "rebounds": 5,
          "assists": 1,
          "steals": 1,
          "blocks": 0,
          "turnovers": 4
        }
      ],
      "description": "Justin Jamel Wright–Foreman (born October 27, 1997) is an American professional basketball player for Iraklis of the Greek Basketball League. He played college basketball for the Hofstra Pride. He was drafted by the Utah Jazz with the 53rd overall pick in the 2019 NBA draft."
    },
    {
      "code": "34196191",
      "name": "Kendrick Nunn",
      "team": "Panathinaikos BC",
      "team_logo": "https://r2.thesportsdb.com/images/media/team/badge/7cdjwz1767366987.png",
      "position": "Point Guard",
      "nationality": "United States",
      "height_cm": 188,
      "height_feet": 6,
      "height_inches": 2,
      "birthdate": "1995-08-03",
      "birthplace": "Chicago, Illinois, U.S.",
      "headshot_url": "https://r2.thesportsdb.com/images/media/player/cutout/z0c1in1731840958.png",
      "games_played": 9,
      "ppg": 15.3,
      "rpg": 2.8,
      "apg": 3.4,
      "game_log": [
        {
          "date": "Tue 30 Dec - 18:30",
          "opponent": "ΜΑΡΟΥΣΙCHERY",
          "home_away": "Away",
          "team_score": 99,
          "opp_score": 89,
          "result": "W",
          "minutes": "00:20:08",
          "points": 14,
          "rebounds": 2,
          "assists": 3,
          "steals": 0,
          "blocks": 0,
          "turnovers": 1
        },
        {
          "date": "Sun 7 Dec - 16:00",
          "opponent": "ΠΑΝΙΩΝΙΟΣCOSMORAMATRAVEL",
          "home_away": "Home",
          "team_score": 110,
          "opp_score": 66,
          "result": "W",
          "minutes": "00:00:00",
          "points": 0,
          "rebounds": 0,
          "assists": 0,
          "steals": 0,
          "blocks": 0,
          "turnovers": 0
        },
        {
          "date": "Sun 5 Oct - 16:00",
          "opponent": "ΠΑΟΚ",
          "home_away": "Home",
          "team_score": 93,
          "opp_score": 83,
          "result": "W",
          "minutes": "00:20:28",
          "points": 12,
          "rebounds": 3,
          "assists": 6,
          "steals": 2,
          "blocks": 1,
          "turnovers": 3
        },
        {
          "date": "Sun 4 Jan - 16:00",
          "opponent": "ΚΑΡΔΙΤΣΑΙΑΠΩΝΙΚΗ",
          "home_away": "Home",
          "team_score": 92,
          "opp_score": 85,
          "result": "W",
          "minutes": "00:30:57",
          "points": 27,
          "rebounds": 2,
          "assists": 6,
          "steals": 0,
          "blocks": 0,
          "turnovers": 3
        },
        {
          "date": "Sun 19 Oct - 16:00",
          "opponent": "ΚΟΛΟΣΣΟΣ HHOTELSCOLLECTION",
          "home_away": "Away",
          "team_score": 90,
          "opp_score": 67,
          "result": "W",
          "minutes": "00:22:00",
          "points": 7,
          "rebounds": 4,
          "assists": 3,
          "steals": 0,
          "blocks": 0,
          "turnovers": 3
        },
        {
          "date": "Sun 16 Nov - 18:15",
          "opponent": "ΑΡΗΣBetsson",
          "home_away": "Home",
          "team_score": 82,
          "opp_score": 77,
          "result": "W",
          "minutes": "00:28:12",
          "points": 19,
          "rebounds": 4,
          "assists": 3,
          "steals": 2,
          "blocks": 0,
          "turnovers": 1
        },
        {
          "date": "Sat 8 Nov - 16:00",
          "opponent": "ΠΕΡΙΣΤΕΡΙBetsson",
          "home_away": "Away",
          "team_score": 89,
          "opp_score": 72,
          "result": "W",
          "minutes": "00:25:12",
          "points": 27,
          "rebounds": 4,
          "assists": 3,
          "steals": 0,
          "blocks": 1,
          "turnovers": 2
        },
        {
          "date": "Sat 22 Nov - 16:00",
          "opponent": "ΜΥΚΟΝΟΣBetsson BC",
          "home_away": "Away",
          "team_score": 78,
          "opp_score": 65,
          "result": "W",
          "minutes": "00:31:21",
          "points": 23,
          "rebounds": 5,
          "assists": 6,
          "steals": 6,
          "blocks": 0,
          "turnovers": 2
        },
        {
          "date": "Sat 13 Dec - 20:30",
          "opponent": "ΑΕΚ",
          "home_away": "Away",
          "team_score": 101,
          "opp_score": 63,
          "result": "W",
          "minutes": "00:16:41",
          "points": 9,
          "rebounds": 1,
          "assists": 1,
          "steals": 0,
          "blocks": 0,
          "turnovers": 2
        }
      ],
      "description": "Kendrick Melvin Nunn (born August 3, 1995) is an American professional basketball player for Panathinaikos of the Greek Basket League and the EuroLeague. He played college basketball for the Illinois Fighting Illini and the Oakland Golden Grizzlies.\r\n\r\nNunn played three seasons at the University of Illinois, where he was named to the 2013–14 Big Ten All-Freshman team. He was dismissed from the Illini after the 2015–16 season, and had to sit out a season after transferring to Oakland University due to National Collegiate Athletic Association (NCAA) transfer rules. He won the 2018 Horizon League Men's Basketball Player of the Year award at Oakland after leading the nation in three-point shots made per game.\r\n\r\nAfter going undrafted in the 2018 NBA draft, Nunn spent the 2018–19 season with the Santa Cruz Warriors of the NBA G League. In April 2019, he signed with the Miami Heat and reached the 2020 NBA Finals. He was also named to the NBA All-Rookie First Team. In August 2021, Nunn signed with the Los Angeles Lakers. However, he missed the entire 2021–22 season with a knee injury. In January 2023, he was traded to the Washington Wizards."
    },
    {
      "code": "34161170",
      "name": "Kenneth Faried",
      "team": "Panathinaikos BC",
      "team_logo": "https://r2.thesportsdb.com/images/media/team/badge/7cdjwz1767366987.png",
      "position": "Power Forward",
      "nationality": "United States",
      "height_cm": 202,
      "height_feet": 6,
      "height_inches": 7,
      "birthdate": "1989-11-19",
      "birthplace": "Newark, New Jersey",
      "headshot_url": "https://r2.thesportsdb.com/images/media/player/cutout/5abexo1762975929.png",
      "games_played": 7,
      "ppg": 6.9,
      "rpg": 5.0,
      "apg": 0.4,
      "game_log": [
        {
          "date": "Sun 8 Feb - 16:00",
          "opponent": "ΚΑΡΔΙΤΣΑΙΑΠΩΝΙΚΗ",
          "home_away": "Away",
          "team_score": 78,
          "opp_score": 53,
          "result": "W",
          "minutes": "00:15:31",
          "points": 2,
          "rebounds": 3,
          "assists": 0,
          "steals": 0,
          "blocks": 4,
          "turnovers": 1
        },
        {
          "date": "Sun 7 Dec - 16:00",
          "opponent": "ΠΑΝΙΩΝΙΟΣCOSMORAMATRAVEL",
          "home_away": "Home",
          "team_score": 110,
          "opp_score": 66,
          "result": "W",
          "minutes": "00:17:02",
          "points": 9,
          "rebounds": 6,
          "assists": 1,
          "steals": 0,
          "blocks": 0,
          "turnovers": 1
        },
        {
          "date": "Sun 25 Jan - 15:45",
          "opponent": "ΜΑΡΟΥΣΙCHERY",
          "home_away": "Home",
          "team_score": 92,
          "opp_score": 81,
          "result": "W",
          "minutes": "00:19:19",
          "points": 10,
          "rebounds": 6,
          "assists": 1,
          "steals": 1,
          "blocks": 2,
          "turnovers": 0
        },
        {
          "date": "Sun 16 Nov - 18:15",
          "opponent": "ΑΡΗΣBetsson",
          "home_away": "Home",
          "team_score": 82,
          "opp_score": 77,
          "result": "W",
          "minutes": "00:33:04",
          "points": 13,
          "rebounds": 9,
          "assists": 1,
          "steals": 1,
          "blocks": 1,
          "turnovers": 1
        },
        {
          "date": "Sat 22 Nov - 16:00",
          "opponent": "ΜΥΚΟΝΟΣBetsson BC",
          "home_away": "Away",
          "team_score": 78,
          "opp_score": 65,
          "result": "W",
          "minutes": "00:22:52",
          "points": 10,
          "rebounds": 9,
          "assists": 0,
          "steals": 1,
          "blocks": 2,
          "turnovers": 2
        },
        {
          "date": "Sat 20 Dec - 18:15",
          "opponent": "ΗΡΑΚΛΗΣ",
          "home_away": "Home",
          "team_score": 97,
          "opp_score": 82,
          "result": "W",
          "minutes": "00:10:48",
          "points": 0,
          "rebounds": 0,
          "assists": 0,
          "steals": 0,
          "blocks": 1,
          "turnovers": 0
        },
        {
          "date": "Sat 13 Dec - 20:30",
          "opponent": "ΑΕΚ",
          "home_away": "Away",
          "team_score": 101,
          "opp_score": 63,
          "result": "W",
          "minutes": "00:08:21",
          "points": 4,
          "rebounds": 2,
          "assists": 0,
          "steals": 0,
          "blocks": 0,
          "turnovers": 1
        }
      ],
      "description": "Kenneth Bernard Faried Lewis (/fərˈiːd/ fə-REED; born November 19, 1989) is an American professional basketball player for Panathinaikos of the Greek Basketball League and the EuroLeague. Known as \"the Manimal\" due to his hustle on the court, he attended Morehead State University for four years, twice being named the Ohio Valley Conference Player of the Year. He finished his collegiate career as the NCAA all-time leading rebounder in the post-1973 era with 1,673 rebounds, although he was surpassed by Armando Bacot in 2024. He was selected 22nd overall in the 2011 NBA draft by the Denver Nuggets.\r\n\r\nFaried played for the United States national team at the 2014 FIBA Basketball World Cup, where he won a gold medal and was named to the All-Tournament Team."
    },
    {
      "code": "34165430",
      "name": "Monté Morris",
      "team": "Olympiacos BC",
      "team_logo": "https://r2.thesportsdb.com/images/media/team/logo/r7b1lk1720039385.png",
      "position": "Point Guard",
      "nationality": "United States",
      "height_cm": 188,
      "height_feet": 6,
      "height_inches": 2,
      "birthdate": "1995-06-27",
      "birthplace": "Grand Rapids, Michigan",
      "headshot_url": "https://r2.thesportsdb.com/images/media/player/cutout/u0d0eu1766827787.png",
      "games_played": 2,
      "ppg": 8.0,
      "rpg": 2.0,
      "apg": 3.0,
      "game_log": [
        {
          "date": "Sun 4 Jan - 13:00",
          "opponent": "ΑΡΗΣBetsson",
          "home_away": "Away",
          "team_score": 95,
          "opp_score": 84,
          "result": "W",
          "minutes": "00:24:37",
          "points": 8,
          "rebounds": 2,
          "assists": 2,
          "steals": 0,
          "blocks": 0,
          "turnovers": 0
        },
        {
          "date": "Sun 21 Dec - 13:00",
          "opponent": "ΚΟΛΟΣΣΟΣ HHOTELSCOLLECTION",
          "home_away": "Home",
          "team_score": 100,
          "opp_score": 86,
          "result": "W",
          "minutes": "00:22:17",
          "points": 8,
          "rebounds": 2,
          "assists": 4,
          "steals": 2,
          "blocks": 0,
          "turnovers": 1
        }
      ],
      "description": "Monté Robert Morris (/ˈmɒnteɪ/ MON-tay; born June 27, 1995) is an American professional basketball player for Olympiacos of the Greek Basketball League (GBL) and the EuroLeague. He played college basketball for the Iowa State Cyclones."
    },
    {
      "code": "34219753",
      "name": "RaiQuan Gray",
      "team": "AEK BC",
      "team_logo": "https://r2.thesportsdb.com/images/media/team/badge/qm1nux1753264474.png",
      "position": "Power Forward",
      "nationality": "United States",
      "height_cm": 200,
      "height_feet": 6,
      "height_inches": 6,
      "birthdate": "1999-07-07",
      "birthplace": "Parkland, Florida, U.S.",
      "headshot_url": "https://r2.thesportsdb.com/images/media/player/cutout/1oxr9j1688818346.png",
      "games_played": 16,
      "ppg": 12.8,
      "rpg": 3.8,
      "apg": 1.6,
      "game_log": [
        {
          "date": "Sun 9 Nov - 13:00",
          "opponent": "ΠΑΟΚ",
          "home_away": "Home",
          "team_score": 76,
          "opp_score": 78,
          "result": "L",
          "minutes": "00:28:18",
          "points": 16,
          "rebounds": 2,
          "assists": 1,
          "steals": 3,
          "blocks": 1,
          "turnovers": 3
        },
        {
          "date": "Sun 7 Dec - 13:00",
          "opponent": "ΟΛΥΜΠΙΑΚΟΣ",
          "home_away": "Away",
          "team_score": 93,
          "opp_score": 100,
          "result": "L",
          "minutes": "00:34:08",
          "points": 8,
          "rebounds": 3,
          "assists": 4,
          "steals": 0,
          "blocks": 2,
          "turnovers": 3
        },
        {
          "date": "Sun 12 Oct - 13:00",
          "opponent": "ΠΑΝΙΩΝΙΟΣCOSMORAMATRAVEL",
          "home_away": "Home",
          "team_score": 93,
          "opp_score": 73,
          "result": "W",
          "minutes": "00:23:13",
          "points": 4,
          "rebounds": 2,
          "assists": 1,
          "steals": 2,
          "blocks": 1,
          "turnovers": 0
        },
        {
          "date": "Sun 11 Jan - 13:00",
          "opponent": "ΜΥΚΟΝΟΣBetsson BC",
          "home_away": "Home",
          "team_score": 90,
          "opp_score": 65,
          "result": "W",
          "minutes": "00:32:49",
          "points": 21,
          "rebounds": 6,
          "assists": 0,
          "steals": 2,
          "blocks": 0,
          "turnovers": 1
        },
        {
          "date": "Sat 7 Feb - 18:00",
          "opponent": "ΜΑΡΟΥΣΙCHERY",
          "home_away": "Home",
          "team_score": 83,
          "opp_score": 74,
          "result": "W",
          "minutes": "00:36:34",
          "points": 20,
          "rebounds": 5,
          "assists": 1,
          "steals": 1,
          "blocks": 1,
          "turnovers": 2
        },
        {
          "date": "Sat 4 Oct - 16:00",
          "opponent": "ΚΟΛΟΣΣΟΣ HHOTELSCOLLECTION",
          "home_away": "Away",
          "team_score": 87,
          "opp_score": 85,
          "result": "W",
          "minutes": "00:23:04",
          "points": 11,
          "rebounds": 3,
          "assists": 1,
          "steals": 2,
          "blocks": 0,
          "turnovers": 0
        },
        {
          "date": "Sat 31 Jan - 18:15",
          "opponent": "ΚΟΛΟΣΣΟΣ HHOTELSCOLLECTION",
          "home_away": "Home",
          "team_score": 96,
          "opp_score": 83,
          "result": "W",
          "minutes": "00:31:09",
          "points": 16,
          "rebounds": 4,
          "assists": 3,
          "steals": 2,
          "blocks": 1,
          "turnovers": 6
        },
        {
          "date": "Sat 3 Jan - 18:15",
          "opponent": "ΠΡΟΜΗΘΕΑΣΠΑΤΡΑΣΒΙΚΟΣCOLA",
          "home_away": "Away",
          "team_score": 94,
          "opp_score": 86,
          "result": "W",
          "minutes": "00:26:40",
          "points": 18,
          "rebounds": 4,
          "assists": 1,
          "steals": 2,
          "blocks": 0,
          "turnovers": 3
        },
        {
          "date": "Sat 27 Dec - 16:00",
          "opponent": "ΑΡΗΣBetsson",
          "home_away": "Home",
          "team_score": 82,
          "opp_score": 76,
          "result": "W",
          "minutes": "00:30:25",
          "points": 15,
          "rebounds": 4,
          "assists": 3,
          "steals": 1,
          "blocks": 0,
          "turnovers": 2
        },
        {
          "date": "Sat 25 Oct - 17:30",
          "opponent": "ΗΡΑΚΛΗΣ",
          "home_away": "Away",
          "team_score": 82,
          "opp_score": 61,
          "result": "W",
          "minutes": "00:29:21",
          "points": 10,
          "rebounds": 5,
          "assists": 1,
          "steals": 2,
          "blocks": 0,
          "turnovers": 2
        },
        {
          "date": "Sat 20 Dec - 16:00",
          "opponent": "ΜΥΚΟΝΟΣBetsson BC",
          "home_away": "Away",
          "team_score": 77,
          "opp_score": 76,
          "result": "W",
          "minutes": "00:23:31",
          "points": 10,
          "rebounds": 4,
          "assists": 0,
          "steals": 1,
          "blocks": 0,
          "turnovers": 1
        },
        {
          "date": "Sat 18 Oct - 16:00",
          "opponent": "ΚΑΡΔΙΤΣΑΙΑΠΩΝΙΚΗ",
          "home_away": "Home",
          "team_score": 77,
          "opp_score": 62,
          "result": "W",
          "minutes": "00:24:06",
          "points": 12,
          "rebounds": 3,
          "assists": 0,
          "steals": 2,
          "blocks": 0,
          "turnovers": 0
        },
        {
          "date": "Sat 17 Jan - 18:15",
          "opponent": "ΚΑΡΔΙΤΣΑΙΑΠΩΝΙΚΗ",
          "home_away": "Away",
          "team_score": 79,
          "opp_score": 71,
          "result": "W",
          "minutes": "00:27:48",
          "points": 5,
          "rebounds": 5,
          "assists": 2,
          "steals": 1,
          "blocks": 1,
          "turnovers": 2
        },
        {
          "date": "Sat 15 Nov - 18:15",
          "opponent": "ΜΑΡΟΥΣΙCHERY",
          "home_away": "Away",
          "team_score": 103,
          "opp_score": 82,
          "result": "W",
          "minutes": "00:35:02",
          "points": 25,
          "rebounds": 6,
          "assists": 2,
          "steals": 4,
          "blocks": 0,
          "turnovers": 2
        },
        {
          "date": "Sat 13 Dec - 20:30",
          "opponent": "ΠΑΝΑΘΗΝΑΪΚΟΣAKTOR",
          "home_away": "Home",
          "team_score": 63,
          "opp_score": 101,
          "result": "L",
          "minutes": "00:33:58",
          "points": 10,
          "rebounds": 1,
          "assists": 2,
          "steals": 1,
          "blocks": 0,
          "turnovers": 0
        },
        {
          "date": "Sat 1 Nov - 16:00",
          "opponent": "ΠΕΡΙΣΤΕΡΙBetsson",
          "home_away": "Away",
          "team_score": 66,
          "opp_score": 79,
          "result": "L",
          "minutes": "00:23:52",
          "points": 3,
          "rebounds": 3,
          "assists": 4,
          "steals": 0,
          "blocks": 0,
          "turnovers": 2
        }
      ],
      "description": "RaiQuan Kelvan Gray (born July 7, 1999) is an American professional basketball player for AEK Athens of the Greek Basketball League (GBL) and the Basketball Champions League (BCL). He played college basketball for the Florida State Seminoles."
    },
    {
      "code": "34244640",
      "name": "Rayjon Tucker",
      "team": "AEK BC",
      "team_logo": "https://r2.thesportsdb.com/images/media/team/badge/qm1nux1753264474.png",
      "position": "Shooting Guard",
      "nationality": "United States",
      "height_cm": 191,
      "height_feet": 6,
      "height_inches": 3,
      "birthdate": "1997-09-24",
      "birthplace": "Charlotte, North Carolina, USA",
      "headshot_url": "https://r2.thesportsdb.com/images/media/player/cutout/zimesv1737206782.png",
      "games_played": 0,
      "ppg": 0,
      "rpg": 0,
      "apg": 0,
      "game_log": [],
      "description": "Rayjon Tucker (born September 24, 1997) is an American professional basketball player for AEK Athens of the Greek Basketball League (GBL). He played college basketball for the Florida Gulf Coast Eagles and the Little Rock Trojans."
    },
    {
      "code": "34194076",
      "name": "Sharife Cooper",
      "team": "Aris BC",
      "team_logo": "https://r2.thesportsdb.com/images/media/team/badge/l0tssh1739659466.png",
      "position": "Point Guard",
      "nationality": "United States",
      "height_cm": 185,
      "height_feet": 6,
      "height_inches": 0,
      "birthdate": "2001-06-11",
      "birthplace": "Newark, New Jersey, U.S.",
      "headshot_url": "https://r2.thesportsdb.com/images/media/player/cutout/cwkp4m1666548260.png",
      "games_played": 0,
      "ppg": 0,
      "rpg": 0,
      "apg": 0,
      "game_log": [],
      "description": "Sharife Omar Cooper (born June 11, 2001) is an American professional basketball player for Aris Thessaloniki of the Greek Basketball League (GBL) and the EuroCup. He played college basketball for the Auburn Tigers."
    }
  ]
}