{
  "export_date": "2026-02-02T18:51:43.077797",
  "season": "2025-26",
  "league": "Lega Basket Serie A",
  "player_count": 43,
  "players": [
    {
      "code": "34201904",
      "name": "A.J. Pacher",
      "team": "Pallacanestro Trieste",
      "team_code": "136333",
      "position": "Power Forward",
      "jersey": "2",
      "height_feet": 6,
      "height_inches": 10,
      "birth_date": "1992-02-17",
      "hometown": "Vandalia",
      "hometown_state": null,
      "college": null,
      "high_school": null,
      "headshot_url": "https://r2.thesportsdb.com/images/media/player/thumb/bxpf1u1665853779.jpg",
      "games_played": 0,
      "ppg": 0.0,
      "rpg": 0.0,
      "apg": 0.0
    },
    {
      "code": "34397083",
      "name": "Aamir Simms",
      "team": "Napoli Basket",
      "team_code": "143962",
      "position": "Power Forward",
      "jersey": "25",
      "height_feet": 6,
      "height_inches": 8,
      "birth_date": "1999-02-17",
      "hometown": "East Orange, United States",
      "hometown_state": "United States",
      "college": "Clemson Tigers",
      "high_school": null,
      "headshot_url": "https://r2.thesportsdb.com/images/media/player/thumb/eibd591756821833.jpg",
      "games_played": 15,
      "ppg": 12.1,
      "rpg": 6.0,
      "apg": 2.6
    },
    {
      "code": "34165406",
      "name": "Alfonzo McKinnie",
      "team": "Dinamo Basket Sassari",
      "team_code": "135380",
      "position": "Small Forward",
      "jersey": "28",
      "height_feet": 6,
      "height_inches": 7,
      "birth_date": "1992-09-17",
      "hometown": "Chicago, Illinois",
      "hometown_state": "Illinois",
      "college": "Eastern Illinois University, University of Wisconsin–Green Bay",
      "high_school": null,
      "headshot_url": "https://r2.thesportsdb.com/images/media/player/thumb/q3stjr1550050246.jpg",
      "games_played": 0,
      "ppg": 0.0,
      "rpg": 0.0,
      "apg": 0.0
    },
    {
      "code": "34196240",
      "name": "Armoni Brooks",
      "team": "Olimpia Milano",
      "team_code": "135383",
      "position": "Shooting Guard",
      "jersey": "12",
      "height_feet": 6,
      "height_inches": 3,
      "birth_date": "1998-06-05",
      "hometown": "Waco, Texas",
      "hometown_state": "Texas",
      "college": "Houston Cougars",
      "high_school": null,
      "headshot_url": "https://r2.thesportsdb.com/images/media/player/thumb/qz9oe81700219475.jpg",
      "games_played": 19,
      "ppg": 16.3,
      "rpg": 4.5,
      "apg": 1.7
    },
    {
      "code": "34348421",
      "name": "Brandon Taylor",
      "team": "Virtus Pallacanestro Bologna",
      "team_code": "135386",
      "position": "Point Guard",
      "jersey": "11",
      "height_feet": 5,
      "height_inches": 10,
      "birth_date": "1994-01-08",
      "hometown": "West Hollywood, California",
      "hometown_state": "California",
      "college": "He played",
      "high_school": null,
      "headshot_url": "https://r2.thesportsdb.com/images/media/player/thumb/ns7eee1753119512.jpg",
      "games_played": 12,
      "ppg": 6.8,
      "rpg": 1.1,
      "apg": 3.8
    },
    {
      "code": "34253814",
      "name": "Carsen Edwards",
      "team": "Virtus Pallacanestro Bologna",
      "team_code": "135386",
      "position": "Point Guard",
      "jersey": "",
      "height_feet": 5,
      "height_inches": 11,
      "birth_date": "1998-03-12",
      "hometown": "Houston, Texas",
      "hometown_state": "Texas",
      "college": "Purdue Boilermakers",
      "high_school": null,
      "headshot_url": "https://r2.thesportsdb.com/images/media/player/thumb/jvpe5l1732558983.jpg",
      "games_played": 15,
      "ppg": 15.1,
      "rpg": 1.8,
      "apg": 3.7
    },
    {
      "code": "34216199",
      "name": "Chris Dowe",
      "team": "Pallacanestro Brescia",
      "team_code": "135915",
      "position": "Point Guard",
      "jersey": "5",
      "height_feet": 6,
      "height_inches": 2,
      "birth_date": "1991-08-26",
      "hometown": "Louisville, Kentucky",
      "hometown_state": "Kentucky",
      "college": "Bellarmine University before playing professionally in Portugal",
      "high_school": null,
      "headshot_url": "https://r2.thesportsdb.com/images/media/player/thumb/dzfiyz1720331559.jpg",
      "games_played": 3,
      "ppg": 7.0,
      "rpg": 1.0,
      "apg": 0.0
    },
    {
      "code": "34179798",
      "name": "Christian Burns",
      "team": "Pallacanestro Brescia",
      "team_code": "135915",
      "position": "Power Forward",
      "jersey": "23",
      "height_feet": 6,
      "height_inches": 8,
      "birth_date": "1985-09-04",
      "hometown": "Trenton, New Jersey",
      "hometown_state": "New Jersey",
      "college": null,
      "high_school": null,
      "headshot_url": "https://r2.thesportsdb.com/images/media/player/thumb/8efevi1619818282.jpg",
      "games_played": 15,
      "ppg": 4.7,
      "rpg": 2.0,
      "apg": 0.5
    },
    {
      "code": "34244270",
      "name": "Christian Vital",
      "team": "Derthona Basket",
      "team_code": "143963",
      "position": "Guard",
      "jersey": "",
      "height_feet": 6,
      "height_inches": 2,
      "birth_date": "1997-03-21",
      "hometown": "Queens Village, New York",
      "hometown_state": "New York",
      "college": "UConn Huskies",
      "high_school": null,
      "headshot_url": "https://r2.thesportsdb.com/images/media/player/thumb/w727uv1720244761.jpg",
      "games_played": 17,
      "ppg": 19.6,
      "rpg": 3.5,
      "apg": 3.1
    },
    {
      "code": "34202056",
      "name": "Colbey Ross",
      "team": "Pallacanestro Trieste",
      "team_code": "136333",
      "position": "Guard",
      "jersey": "4",
      "height_feet": 6,
      "height_inches": 1,
      "birth_date": "1998-10-22",
      "hometown": "Aurora, Colorado",
      "hometown_state": "Colorado",
      "college": "Pepperdine Waves",
      "high_school": null,
      "headshot_url": "https://r2.thesportsdb.com/images/media/player/thumb/txbgtl1667135720.jpg",
      "games_played": 13,
      "ppg": 10.0,
      "rpg": 2.0,
      "apg": 3.4
    },
    {
      "code": "34201903",
      "name": "Corey Davis",
      "team": "Guerino Vanoli Basket",
      "team_code": "135393",
      "position": "Point Guard",
      "jersey": "5",
      "height_feet": 6,
      "height_inches": 1,
      "birth_date": "1997-06-04",
      "hometown": "Lafayette",
      "hometown_state": null,
      "college": "Houston Cougars",
      "high_school": null,
      "headshot_url": "https://r2.thesportsdb.com/images/media/player/thumb/2fd3bi1665853273.jpg",
      "games_played": 0,
      "ppg": 0.0,
      "rpg": 0.0,
      "apg": 0.0
    },
    {
      "code": "34216143",
      "name": "Darion Atkins",
      "team": "Trento",
      "team_code": "135382",
      "position": "Power Forward",
      "jersey": "44",
      "height_feet": 6,
      "height_inches": 8,
      "birth_date": "1992-09-17",
      "hometown": "Clinton, Maryland",
      "hometown_state": "Maryland",
      "college": "University of Virginia before playing professionally in Israel",
      "high_school": null,
      "headshot_url": "https://r2.thesportsdb.com/images/media/player/thumb/zjl10n1756819458.jpg",
      "games_played": 0,
      "ppg": 0.0,
      "rpg": 0.0,
      "apg": 0.0
    },
    {
      "code": "34179802",
      "name": "David Moss",
      "team": "Pallacanestro Brescia",
      "team_code": "135915",
      "position": "Small Forward",
      "jersey": "34",
      "height_feet": 6,
      "height_inches": 5,
      "birth_date": "1983-09-09",
      "hometown": "Chicago, Illinois",
      "hometown_state": "Illinois",
      "college": null,
      "high_school": null,
      "headshot_url": "https://r2.thesportsdb.com/images/media/player/thumb/nsauwb1619819401.jpg",
      "games_played": 0,
      "ppg": 0.0,
      "rpg": 0.0,
      "apg": 0.0
    },
    {
      "code": "34420595",
      "name": "Demetre Rivers",
      "team": "Pallacanestro Brescia",
      "team_code": "135915",
      "position": "Forward",
      "jersey": "23",
      "height_feet": 6,
      "height_inches": 8,
      "birth_date": "1995-12-07",
      "hometown": null,
      "hometown_state": null,
      "college": null,
      "high_school": null,
      "headshot_url": "https://r2.thesportsdb.com/images/media/player/thumb/twi79f1760037116.jpg",
      "games_played": 22,
      "ppg": 9.1,
      "rpg": 2.4,
      "apg": 0.7
    },
    {
      "code": "34396063",
      "name": "Derrick Alston Jr.",
      "team": "Virtus Pallacanestro Bologna",
      "team_code": "135386",
      "position": "Forward/Center",
      "jersey": "21",
      "height_feet": 6,
      "height_inches": 9,
      "birth_date": "1997-09-17",
      "hometown": "Houston, United States",
      "hometown_state": "United States",
      "college": "Boise State Broncos",
      "high_school": null,
      "headshot_url": "https://r2.thesportsdb.com/images/media/player/thumb/4tc8nh1756820841.jpg",
      "games_played": 17,
      "ppg": 12.1,
      "rpg": 2.9,
      "apg": 0.9
    },
    {
      "code": "34216205",
      "name": "Deshawn Stephens",
      "team": "Dinamo Basket Sassari",
      "team_code": "135380",
      "position": "Forward/Center",
      "jersey": "13",
      "height_feet": 6,
      "height_inches": 8,
      "birth_date": "1989-10-09",
      "hometown": "Los Angeles, California",
      "hometown_state": "California",
      "college": "Santa Monica College, San Diego State before playing professionally in Japan",
      "high_school": null,
      "headshot_url": null,
      "games_played": 9,
      "ppg": 8.9,
      "rpg": 5.3,
      "apg": 0.8
    },
    {
      "code": "34172887",
      "name": "Devin Booker",
      "team": "Olimpia Milano",
      "team_code": "135383",
      "position": "Power Forward",
      "jersey": "6",
      "height_feet": 6,
      "height_inches": 9,
      "birth_date": "1991-02-28",
      "hometown": "Grand Rapids, Michigan",
      "hometown_state": "Michigan",
      "college": "Clemson, played professionally in the National Basketball Association (NBA)",
      "high_school": null,
      "headshot_url": "https://r2.thesportsdb.com/images/media/player/thumb/vyavq41674398318.jpg",
      "games_played": 11,
      "ppg": 8.0,
      "rpg": 3.6,
      "apg": 1.5
    },
    {
      "code": "34216244",
      "name": "Devin Davis",
      "team": "Napoli Basket",
      "team_code": "143962",
      "position": "Forward/Center",
      "jersey": "15",
      "height_feet": 6,
      "height_inches": 7,
      "birth_date": "1995-03-29",
      "hometown": "Indianapolis, Indiana",
      "hometown_state": "Indiana",
      "college": "Indiana",
      "high_school": null,
      "headshot_url": "https://r2.thesportsdb.com/images/media/player/thumb/j1x73r1756820846.jpg",
      "games_played": 0,
      "ppg": 0.0,
      "rpg": 0.0,
      "apg": 0.0
    },
    {
      "code": "34179795",
      "name": "Drew Crawford",
      "team": "Trento",
      "team_code": "135382",
      "position": "Small Forward",
      "jersey": "22",
      "height_feet": 6,
      "height_inches": 4,
      "birth_date": "1990-10-18",
      "hometown": "Naperville, Illinois",
      "hometown_state": "Illinois",
      "college": "Northwestern Wildcats",
      "high_school": null,
      "headshot_url": "https://r2.thesportsdb.com/images/media/player/thumb/bpy7xo1619816645.jpg",
      "games_played": 0,
      "ppg": 0.0,
      "rpg": 0.0,
      "apg": 0.0
    },
    {
      "code": "34216246",
      "name": "Elijah Stewart",
      "team": "Napoli Basket",
      "team_code": "143962",
      "position": "Small Forward",
      "jersey": "30",
      "height_feet": 6,
      "height_inches": 5,
      "birth_date": "1995-11-14",
      "hometown": "DeRidder, Louisiana",
      "hometown_state": "Louisiana",
      "college": "USC Trojans",
      "high_school": null,
      "headshot_url": "https://r2.thesportsdb.com/images/media/player/thumb/tldxn01756820706.jpg",
      "games_played": 0,
      "ppg": 0.0,
      "rpg": 0.0,
      "apg": 0.0
    },
    {
      "code": "34197363",
      "name": "Frank Gaines",
      "team": "Pallacanestro Trieste",
      "team_code": "136333",
      "position": "Shooting Guard",
      "jersey": "1",
      "height_feet": 6,
      "height_inches": 3,
      "birth_date": "1990-07-07",
      "hometown": "Fort Lauderdale, Florida",
      "hometown_state": "Florida",
      "college": "Indiana University – Purdue University Fort Wayne",
      "high_school": null,
      "headshot_url": "https://r2.thesportsdb.com/images/media/player/thumb/0pifvz1650698780.jpg",
      "games_played": 0,
      "ppg": 0.0,
      "rpg": 0.0,
      "apg": 0.0
    },
    {
      "code": "34216198",
      "name": "Gerald Robinson",
      "team": "Dinamo Basket Sassari",
      "team_code": "135380",
      "position": "Guard",
      "jersey": "4",
      "height_feet": 6,
      "height_inches": 1,
      "birth_date": "1989-02-10",
      "hometown": "Nashville, Tennessee",
      "hometown_state": "Tennessee",
      "college": null,
      "high_school": null,
      "headshot_url": null,
      "games_played": 0,
      "ppg": 0.0,
      "rpg": 0.0,
      "apg": 0.0
    },
    {
      "code": "34226926",
      "name": "Jacob Gilyard",
      "team": "Pallacanestro Cantù",
      "team_code": "135379",
      "position": "Point Guard",
      "jersey": "",
      "height_feet": 5,
      "height_inches": 8,
      "birth_date": "1998-07-14",
      "hometown": "Kansas City, Missouri",
      "hometown_state": "Missouri",
      "college": "Richmond Spiders",
      "high_school": null,
      "headshot_url": "https://r2.thesportsdb.com/images/media/player/thumb/2rqrl81703953857.jpg",
      "games_played": 13,
      "ppg": 10.5,
      "rpg": 2.6,
      "apg": 6.2
    },
    {
      "code": "34195675",
      "name": "Jamal Jones",
      "team": "Dinamo Basket Sassari",
      "team_code": "135380",
      "position": "Small Forward",
      "jersey": "",
      "height_feet": 6,
      "height_inches": 8,
      "birth_date": "1993-02-17",
      "hometown": "Wynne, Arkansas",
      "hometown_state": "Arkansas",
      "college": "Ole Miss, Texas A&M",
      "high_school": null,
      "headshot_url": "https://r2.thesportsdb.com/images/media/player/thumb/gfbhcy1640778380.jpg",
      "games_played": 0,
      "ppg": 0.0,
      "rpg": 0.0,
      "apg": 0.0
    },
    {
      "code": "34159888",
      "name": "Jamar Smith",
      "team": "Pallacanestro Reggiana",
      "team_code": "135387",
      "position": "Shooting Guard",
      "jersey": "15",
      "height_feet": 6,
      "height_inches": 3,
      "birth_date": "1988-04-07",
      "hometown": "Peoria, Illinois",
      "hometown_state": "Illinois",
      "college": null,
      "high_school": null,
      "headshot_url": "https://r2.thesportsdb.com/images/media/player/thumb/dnkj6a1639088109.jpg",
      "games_played": 8,
      "ppg": 6.4,
      "rpg": 1.2,
      "apg": 2.1
    },
    {
      "code": "34193885",
      "name": "Jaron Johnson",
      "team": "Pallacanestro Varese",
      "team_code": "135388",
      "position": "Small Forward",
      "jersey": "92",
      "height_feet": 6,
      "height_inches": 6,
      "birth_date": "1992-05-05",
      "hometown": "Tyler, Texas",
      "hometown_state": "Texas",
      "college": "Tyler Junior College, Louisiana Tech",
      "high_school": null,
      "headshot_url": "https://r2.thesportsdb.com/images/media/player/thumb/qju4dw1633935370.jpg",
      "games_played": 0,
      "ppg": 0.0,
      "rpg": 0.0,
      "apg": 0.0
    },
    {
      "code": "34216267",
      "name": "Jeff Brooks",
      "team": "Reyer Venezia Mestre",
      "team_code": "135391",
      "position": "Power Forward",
      "jersey": "23",
      "height_feet": 6,
      "height_inches": 8,
      "birth_date": "1989-06-12",
      "hometown": "Louisville, Kentucky",
      "hometown_state": "Kentucky",
      "college": null,
      "high_school": null,
      "headshot_url": "https://r2.thesportsdb.com/images/media/player/thumb/jolz3y1696759693.jpg",
      "games_played": 16,
      "ppg": 2.6,
      "rpg": 2.8,
      "apg": 0.6
    },
    {
      "code": "34174030",
      "name": "Joe Young",
      "team": "Napoli Basket",
      "team_code": "143962",
      "position": "Point Guard",
      "jersey": "3",
      "height_feet": 6,
      "height_inches": 2,
      "birth_date": "1992-06-27",
      "hometown": "Houston, Texas",
      "hometown_state": "Texas",
      "college": "he played",
      "high_school": null,
      "headshot_url": "https://r2.thesportsdb.com/images/media/player/thumb/70u9i81609844118.jpg",
      "games_played": 0,
      "ppg": 0.0,
      "rpg": 0.0,
      "apg": 0.0
    },
    {
      "code": "34216183",
      "name": "John Petrucelli",
      "team": "Pallacanestro Trapani",
      "team_code": "147252",
      "position": "Shooting Guard",
      "jersey": "11",
      "height_feet": 6,
      "height_inches": 4,
      "birth_date": "1992-10-27",
      "hometown": "Hicksville, New York",
      "hometown_state": "New York",
      "college": "Molloy College before playing professionally in Slovakia",
      "high_school": null,
      "headshot_url": "https://r2.thesportsdb.com/images/media/player/thumb/fej9421740905720.jpg",
      "games_played": 0,
      "ppg": 0.0,
      "rpg": 0.0,
      "apg": 0.0
    },
    {
      "code": "34229630",
      "name": "Jordan Ford",
      "team": "Trento",
      "team_code": "135382",
      "position": "Point Guard",
      "jersey": "5",
      "height_feet": 6,
      "height_inches": 1,
      "birth_date": "1998-05-26",
      "hometown": "Citrus Heights, California",
      "hometown_state": "California",
      "college": "Saint Mary's Gaels",
      "high_school": null,
      "headshot_url": "https://r2.thesportsdb.com/images/media/player/thumb/k9spv71709751273.jpg",
      "games_played": 0,
      "ppg": 0.0,
      "rpg": 0.0,
      "apg": 0.0
    },
    {
      "code": "34216240",
      "name": "Jordan Howard",
      "team": "Napoli Basket",
      "team_code": "143962",
      "position": "Point Guard",
      "jersey": "1",
      "height_feet": 5,
      "height_inches": 11,
      "birth_date": "1996-12-20",
      "hometown": "Chandler, Arizona",
      "hometown_state": "Arizona",
      "college": "Central Arkansas",
      "high_school": null,
      "headshot_url": null,
      "games_played": 0,
      "ppg": 0.0,
      "rpg": 0.0,
      "apg": 0.0
    },
    {
      "code": "34216263",
      "name": "Jordan Parks",
      "team": "Reyer Venezia Mestre",
      "team_code": "135391",
      "position": "Power Forward",
      "jersey": "2",
      "height_feet": 6,
      "height_inches": 7,
      "birth_date": "1994-04-06",
      "hometown": "Staten Island, New York",
      "hometown_state": "New York",
      "college": null,
      "high_school": null,
      "headshot_url": null,
      "games_played": 13,
      "ppg": 12.5,
      "rpg": 4.8,
      "apg": 2.2
    },
    {
      "code": "34244275",
      "name": "Justin Gorham",
      "team": "Derthona Basket",
      "team_code": "143963",
      "position": "Forward",
      "jersey": "",
      "height_feet": 6,
      "height_inches": 7,
      "birth_date": "1998-08-06",
      "hometown": "Columbia, Maryland",
      "hometown_state": "Maryland",
      "college": "Towson Tigers, the Houston Cougars",
      "high_school": null,
      "headshot_url": "https://r2.thesportsdb.com/images/media/player/thumb/hv7qiu1720247626.jpg",
      "games_played": 17,
      "ppg": 8.4,
      "rpg": 5.5,
      "apg": 2.4
    },
    {
      "code": "34216312",
      "name": "Justin Reyes",
      "team": "Pallacanestro Varese",
      "team_code": "135388",
      "position": "Guard/Forward",
      "jersey": "12",
      "height_feet": 6,
      "height_inches": 4,
      "birth_date": "1995-03-16",
      "hometown": "Haverhill, Massachusetts",
      "hometown_state": "Massachusetts",
      "college": null,
      "high_school": null,
      "headshot_url": null,
      "games_played": 0,
      "ppg": 0.0,
      "rpg": 0.0,
      "apg": 0.0
    },
    {
      "code": "34216162",
      "name": "Kenny Gabriel",
      "team": "Pallacanestro Brescia",
      "team_code": "135915",
      "position": "Power Forward",
      "jersey": "1",
      "height_feet": 6,
      "height_inches": 9,
      "birth_date": "1989-07-03",
      "hometown": "Charlotte, North Carolina",
      "hometown_state": "North Carolina",
      "college": "Auburn Tigers",
      "high_school": null,
      "headshot_url": "https://r2.thesportsdb.com/images/media/player/thumb/m33gav1756819278.jpg",
      "games_played": 0,
      "ppg": 0.0,
      "rpg": 0.0,
      "apg": 0.0
    },
    {
      "code": "34202049",
      "name": "Kwan Cheatham",
      "team": "Pallacanestro Reggiana",
      "team_code": "135387",
      "position": "Power Forward",
      "jersey": "55",
      "height_feet": 6,
      "height_inches": 10,
      "birth_date": "1995-08-21",
      "hometown": "Vallejo, California",
      "hometown_state": "California",
      "college": null,
      "high_school": null,
      "headshot_url": "https://r2.thesportsdb.com/images/media/player/thumb/yq95dh1667132648.jpg",
      "games_played": 9,
      "ppg": 9.0,
      "rpg": 3.7,
      "apg": 1.0
    },
    {
      "code": "34194044",
      "name": "Kyle Hines",
      "team": "Olimpia Milano",
      "team_code": "135383",
      "position": "Center",
      "jersey": "42",
      "height_feet": 6,
      "height_inches": 6,
      "birth_date": "1986-09-02",
      "hometown": "Sicklerville, New Jersey",
      "hometown_state": "New Jersey",
      "college": "Hines played college basketball with the UNC Greensboro Spartans of the",
      "high_school": null,
      "headshot_url": "https://r2.thesportsdb.com/images/media/player/thumb/mwuczk1671792752.jpg",
      "games_played": 0,
      "ppg": 0.0,
      "rpg": 0.0,
      "apg": 0.0
    },
    {
      "code": "34216030",
      "name": "Kyle Weems",
      "team": "Derthona Basket",
      "team_code": "143963",
      "position": "Forward",
      "jersey": "34",
      "height_feet": 6,
      "height_inches": 6,
      "birth_date": "1989-08-23",
      "hometown": "Topeka, Kansas",
      "hometown_state": "Kansas",
      "college": "He played collegiately for Missouri State",
      "high_school": null,
      "headshot_url": "https://r2.thesportsdb.com/images/media/player/thumb/ozs46b1720258010.jpg",
      "games_played": 0,
      "ppg": 0.0,
      "rpg": 0.0,
      "apg": 0.0
    },
    {
      "code": "34165411",
      "name": "Langston Galloway",
      "team": "Pallacanestro Trapani",
      "team_code": "147252",
      "position": "Shooting Guard",
      "jersey": "9",
      "height_feet": 6,
      "height_inches": 2,
      "birth_date": "1991-12-09",
      "hometown": "Baton Rouge, Louisiana",
      "hometown_state": "Louisiana",
      "college": "Saint Joseph's Hawks",
      "high_school": null,
      "headshot_url": "https://r2.thesportsdb.com/images/media/player/thumb/v13mt61700218706.jpg",
      "games_played": 0,
      "ppg": 0.0,
      "rpg": 0.0,
      "apg": 0.0
    },
    {
      "code": "34222072",
      "name": "Max Heidegger",
      "team": "Reyer Venezia Mestre",
      "team_code": "135391",
      "position": "Point Guard",
      "jersey": "3",
      "height_feet": 6,
      "height_inches": 3,
      "birth_date": "1997-06-05",
      "hometown": "Los Angeles, California",
      "hometown_state": "California",
      "college": "UC Santa Barbara",
      "high_school": null,
      "headshot_url": "https://r2.thesportsdb.com/images/media/player/thumb/sngtsn1697015194.jpg",
      "games_played": 0,
      "ppg": 0.0,
      "rpg": 0.0,
      "apg": 0.0
    },
    {
      "code": "34216269",
      "name": "Mitchell Watt",
      "team": "Reyer Venezia Mestre",
      "team_code": "135391",
      "position": "Center",
      "jersey": "50",
      "height_feet": 6,
      "height_inches": 10,
      "birth_date": "1989-12-14",
      "hometown": "Goodyear, Arizona",
      "hometown_state": "Arizona",
      "college": "University at Buffalo",
      "high_school": null,
      "headshot_url": "https://r2.thesportsdb.com/images/media/player/thumb/ylckpw1756821133.jpg",
      "games_played": 0,
      "ppg": 0.0,
      "rpg": 0.0,
      "apg": 0.0
    },
    {
      "code": "34265275",
      "name": "Tazé Moore",
      "team": "Pallacanestro Varese",
      "team_code": "135388",
      "position": "Shooting Guard",
      "jersey": "7",
      "height_feet": 6,
      "height_inches": 5,
      "birth_date": "1998-06-29",
      "hometown": "Memphis, Tennessee",
      "hometown_state": "Tennessee",
      "college": "Cal State Bakersfield Roadrunners, the Houston Cougars",
      "high_school": null,
      "headshot_url": "https://r2.thesportsdb.com/images/media/player/thumb/0u59o01739535374.jpg",
      "games_played": 17,
      "ppg": 11.4,
      "rpg": 5.4,
      "apg": 3.8
    },
    {
      "code": "34216152",
      "name": "Trent Lockett",
      "team": "Trento",
      "team_code": "135382",
      "position": "Shooting Guard",
      "jersey": "52",
      "height_feet": 6,
      "height_inches": 5,
      "birth_date": "1990-12-10",
      "hometown": "Golden Valley, Minnesota",
      "hometown_state": "Minnesota",
      "college": "Arizona State, Marquette before playing professionally in the NBA G League",
      "high_school": null,
      "headshot_url": "https://r2.thesportsdb.com/images/media/player/thumb/wxgpg51756819379.jpg",
      "games_played": 0,
      "ppg": 0.0,
      "rpg": 0.0,
      "apg": 0.0
    }
  ]
}