{
  "export_date": "2026-02-02T18:41:04.981361",
  "season": "2025-2026",
  "league": "German Basketball Bundesliga (BBL)",
  "source": "thesportsdb.com",
  "player_count": 13,
  "players": [
    {
      "id": "34253575",
      "name": "Justin Bean",
      "nationality": "United States",
      "position": "Power Forward",
      "birthdate": "1996-11-17",
      "birthplace": "Moore, Oklahoma, U.S.",
      "height": "2.01 m (6 ft 7 in)",
      "height_cm": null,
      "team": "ALBA Berlin",
      "team_id": "135416",
      "team_logo": "https://r2.thesportsdb.com/images/media/team/badge/58osvu1545866407.png",
      "thumb": "https://r2.thesportsdb.com/images/media/player/thumb/dm7gqc1731759058.jpg",
      "cutout": "https://r2.thesportsdb.com/images/media/player/cutout/cz78921731759116.png",
      "description": "Justin Barrus Bean (born November 17, 1996) is an American professional basketball player for Alba Berlin of the German Basketball Bundesliga (BBL) and the EuroLeague. He played college basketball for the Utah State Aggies."
    },
    {
      "id": "34195685",
      "name": "Justinian Jessup",
      "nationality": "United States",
      "position": "Shooting Guard",
      "birthdate": "1998-05-23",
      "birthplace": "Longmont, Colorado",
      "height": "1.98 m (6 ft 6 in)",
      "height_cm": null,
      "team": "Bayern München Basketball",
      "team_id": "135424",
      "team_logo": "https://r2.thesportsdb.com/images/media/team/badge/z2r3eh1678017187.png",
      "thumb": "https://r2.thesportsdb.com/images/media/player/thumb/gad5lv1761386371.jpg",
      "cutout": "https://r2.thesportsdb.com/images/media/player/cutout/rgew9x1761386314.png",
      "description": "Justinian Jessup (born May 23, 1998) is an American professional basketball player for Bayern Munich of the German Basketball Bundesliga (BBL) and the EuroLeague. He played college basketball for the Boise State Broncos and was selected by the Golden State Warriors with the 51st overall pick in the 2020 NBA draft."
    },
    {
      "id": "34178814",
      "name": "Barry Brown",
      "nationality": "United States",
      "position": "Shooting Guard",
      "birthdate": "1996-12-21",
      "birthplace": null,
      "height": null,
      "height_cm": null,
      "team": "Ludwigsburg",
      "team_id": "135427",
      "team_logo": "https://r2.thesportsdb.com/images/media/team/badge/6guil91488108871.png",
      "thumb": null,
      "cutout": null,
      "description": null
    },
    {
      "id": "34181117",
      "name": "John Patrick",
      "nationality": "United States",
      "position": "Manager",
      "birthdate": "1968-02-29",
      "birthplace": null,
      "height": null,
      "height_cm": null,
      "team": "Ludwigsburg",
      "team_id": "135427",
      "team_logo": "https://r2.thesportsdb.com/images/media/team/badge/6guil91488108871.png",
      "thumb": "https://r2.thesportsdb.com/images/media/player/thumb/3oly3b1622392510.jpg",
      "cutout": null,
      "description": null
    },
    {
      "id": "34178811",
      "name": "Jordan Hulls",
      "nationality": "United States",
      "position": "Point Guard",
      "birthdate": "1990-04-16",
      "birthplace": null,
      "height": null,
      "height_cm": null,
      "team": "Ludwigsburg",
      "team_id": "135427",
      "team_logo": "https://r2.thesportsdb.com/images/media/team/badge/6guil91488108871.png",
      "thumb": null,
      "cutout": null,
      "description": null
    },
    {
      "id": "34198763",
      "name": "Justin Simon",
      "nationality": "United States",
      "position": "Shooting Guard",
      "birthdate": "1996-05-06",
      "birthplace": "Los Angeles, California, USA",
      "height": "6 ft 5 in (1.96 m)",
      "height_cm": null,
      "team": "Ludwigsburg",
      "team_id": "135427",
      "team_logo": "https://r2.thesportsdb.com/images/media/team/badge/6guil91488108871.png",
      "thumb": "https://r2.thesportsdb.com/images/media/player/thumb/7dgfcy1737803942.jpg",
      "cutout": "https://r2.thesportsdb.com/images/media/player/cutout/28mvl41737804134.png",
      "description": "Justin Simon (born May 6, 1996) is an American professional basketball player for Riesen Ludwigsburg of the German Basketball Bundesliga. He played college basketball for St. John's."
    },
    {
      "id": "34165419",
      "name": "Khyri Thomas",
      "nationality": "United States",
      "position": "Shooting Guard",
      "birthdate": "1996-05-08",
      "birthplace": "Cupertino, California",
      "height": "6 ft 3 in (1.91 m)",
      "height_cm": null,
      "team": "Mitteldeutscher BC",
      "team_id": "135428",
      "team_logo": "https://r2.thesportsdb.com/images/media/team/badge/y4h9ox1714562760.png",
      "thumb": "https://r2.thesportsdb.com/images/media/player/thumb/aq2th71702925399.jpg",
      "cutout": "https://r2.thesportsdb.com/images/media/player/cutout/62frc41550019412.png",
      "description": "Khyri Jaquan Thomas (born May 8, 1996) is an American professional basketball player for Petkim Spor of the Basketbol Süper Ligi (BSL). He played college basketball for the Creighton Bluejays. He was drafted 38th overall by the Philadelphia 76ers in the 2018 NBA draft and then traded to the Detroit Pistons."
    },
    {
      "id": "34179303",
      "name": "Derrick Allen",
      "nationality": "United States",
      "position": "Manager",
      "birthdate": "1980-06-17",
      "birthplace": "",
      "height": "201 cm",
      "height_cm": null,
      "team": "Rasta Vechta",
      "team_id": "136335",
      "team_logo": "https://r2.thesportsdb.com/images/media/team/badge/ukssyu1714562769.png",
      "thumb": "https://r2.thesportsdb.com/images/media/player/thumb/aof9ww1629447676.jpg",
      "cutout": "https://r2.thesportsdb.com/images/media/player/cutout/o8o0861629447737.png",
      "description": "Derrick Dewayne Allen (born July 17, 1980) is an American professional basketball coach and former player. He was most recently the head coach for Rasta Vechta of the ProA.\r\n\r\nAllen launched his professional basketball career in Iceland, playing for Keflavík in the 2003–04 campaign. He was a key player in Keflavík's double-winning campaign (national championship and cup competition), turning in averages of 23.4 points and 10.5 rebounds in league play. In eight games of the FIBA Europe Cup (FIBA EuroCup Challenge), he averaged 26.6 points and 9.4 boards a contest.\r\n\r\nIn the following years, Allen made his mark in the German Basketball Bundesliga, playing for BG Karlsruhe, Bayer Giants Leverkusen, the Skyliners Frankfurt and Alba Berlin. He garnered Eurobasket.com All-German Bundesliga Forward of the Year honors in 2008 and was a Eurobasket.com All-German Bundesliga First Team selection in 2008, 2010 and 2011. He reached the Bundesliga finals with Frankfurt in 2010 and with Berlin in 2011. Over the years, Allen made multiple appearances in international competitions such as the EuroCup, the FIBA EuroChallenge and the FIBA Europe Cup (FIBA EuroCup Challenge).\r\n\r\nAfter spending the 2012–13 season with Belgian powerhouse Spirou BC Charleroi, Allen returned to Germany, enjoying stints with Eisbären Bremerhaven, Basketball Löwen Braunschweig and SC Rasta Vechta. He was part of Vechta's Bundesliga promotion-winning side in 2016. At the end of the 2016–17 Bundesliga season, his Vechta team had to accept relegation from the German top-tier. Allen signed with another BBL team, Science City Jena on May 23, 2017.\r\n\r\nAllen announced his retirement from professional basketball in August 2019.\r\n\r\nIn September 2019, he was named assistant coach at German Bundesliga side SC Rasta Vechta. He stayed on that job until the end of the 2019–20 season. On August 11, 2020, he has re-signed with Rasta Vechta. Allen was promoted to the head coaching role on March 29, 2021 following the firing of Thomas Päch. Allen's Vechta team was relegated to the German second-tier ProA at the conclusion of the 2020–21 season. He was released in October 2021 after five straight losses."
    },
    {
      "id": "34165790",
      "name": "Wes Iwundu",
      "nationality": "United States",
      "position": "Small Forward",
      "birthdate": "1994-12-20",
      "birthplace": "Houston, Texas",
      "height": "6 ft 7 in (2.01 m)",
      "height_cm": null,
      "team": "Rasta Vechta",
      "team_id": "136335",
      "team_logo": "https://r2.thesportsdb.com/images/media/team/badge/ukssyu1714562769.png",
      "thumb": "https://r2.thesportsdb.com/images/media/player/thumb/jjqymn1550152372.jpg",
      "cutout": "https://r2.thesportsdb.com/images/media/player/cutout/tew7p01549989188.png",
      "description": "Wesley Deshawn Iwundu (born December 20, 1994) is an American professional basketball player for Rasta Vechta of the German Bundesliga. He played college basketball for the Kansas State Wildcats."
    },
    {
      "id": "34193921",
      "name": "JeQuan Lewis",
      "nationality": "United States",
      "position": "Point Guard",
      "birthdate": "1994-09-04",
      "birthplace": "Dickson, USA",
      "height": "1.85 m (6 ft 1 in)",
      "height_cm": null,
      "team": "Rostock Seawolves",
      "team_id": "144604",
      "team_logo": "https://r2.thesportsdb.com/images/media/team/badge/8rkn4b1714562777.png",
      "thumb": "https://r2.thesportsdb.com/images/media/player/thumb/wihrq31737805523.jpg",
      "cutout": "https://r2.thesportsdb.com/images/media/player/cutout/ztwqps1737805485.png",
      "description": "JeQuan Demonte Lewis (born September 4, 1994) is an American professional basketball player for Rostock Seawolves of the Basketball Bundesliga (BBL). He played college basketball for VCU."
    },
    {
      "id": "34178819",
      "name": "Aubrey Dawkins",
      "nationality": "United States",
      "position": "Small Forward",
      "birthdate": "1995-05-08",
      "birthplace": "Durham, USA",
      "height": "1.98 m (6 ft 6 in)",
      "height_cm": null,
      "team": "s.Oliver Würzburg",
      "team_id": "135918",
      "team_logo": "https://r2.thesportsdb.com/images/media/team/badge/saynmd1677762541.png",
      "thumb": "https://r2.thesportsdb.com/images/media/player/thumb/rnxwtg1737736254.jpg",
      "cutout": null,
      "description": "Aubrey Lafell Dawkins (born May 8, 1995) is an American professional basketball player for Würzburg Baskets of the Basketball Bundesliga. He played college basketball for the UCF Knights, transferring to UCF after completing his sophomore season for the 2015–16 Michigan Wolverines. He is the son of Johnny Dawkins who became the UCF coach following the 2015–16 NCAA Division I men's basketball season.\r\n\r\nDawkins was raised in North Carolina until spending his high school years in Northern California at St. Francis High School and Palo Alto High School and a postgraduate year in New England at New Hampton Prep. As a collegiate freshman for the 2014–15 Wolverines, he began the season on the bench, but became a starter when injuries plagued the team in January 2015. In his more prominent role later in the season, Dawkins led the 2014–15 Big Ten Conference in effective field goal percentage and true shooting percentage during conference play."
    },
    {
      "id": "34178820",
      "name": "Mark Ogden",
      "nationality": "United States",
      "position": "Center",
      "birthdate": "1994-10-07",
      "birthplace": null,
      "height": null,
      "height_cm": null,
      "team": "s.Oliver Würzburg",
      "team_id": "135918",
      "team_logo": "https://r2.thesportsdb.com/images/media/team/badge/saynmd1677762541.png",
      "thumb": null,
      "cutout": null,
      "description": null
    },
    {
      "id": "34196235",
      "name": "Joe Wieskamp",
      "nationality": "United States",
      "position": "Shooting Guard",
      "birthdate": "1999-08-23",
      "birthplace": "Muscatine, Iowa, U.S.",
      "height": "6 ft 6 in (1.98 m)",
      "height_cm": null,
      "team": "Science City Jena",
      "team_id": "135919",
      "team_logo": "https://r2.thesportsdb.com/images/media/team/badge/wvd2im1759138234.png",
      "thumb": "https://r2.thesportsdb.com/images/media/player/thumb/r6p8fa1700169122.jpg",
      "cutout": "https://r2.thesportsdb.com/images/media/player/cutout/d036u91700169200.png",
      "description": "Joseph Hinman Wieskamp (born August 23, 1999) is an American professional basketball player for Science City Jena of the German Basketball Bundesliga (BBL). He played college basketball for the Iowa Hawkeyes before being drafted 41st overall in the 2021 NBA draft by the San Antonio Spurs."
    }
  ]
}